[{"round_no": 0, "pre_train": {"ts": 1682539456.297751}, "post_train": {"ts": 1682539493.3026423, "eval:loss": 1.1673414707183838, "eval:acc": 0.6396396160125732, "eval:f1 micro": 0.62, "eval:precision micro": 0.71, "eval:recall micro": 0.55, "eval:f1 macro": 0.49, "eval:precision macro": 0.65, "eval:recall macro": 0.48, "eval:f1 weighted": 0.56, "eval:precision weighted": 0.7, "eval:recall weighted": 0.55}, "pre_update": {}, "post_update": {}}, {"round_no": 1, "pre_train": {"ts": 1682539519.6633785, "eval:loss": 0.8968318700790405, "eval:acc": 0.7387387156486511, "eval:f1 micro": 0.75, "eval:precision micro": 0.81, "eval:recall micro": 0.69, "eval:f1 macro": 0.7, "eval:precision macro": 0.74, "eval:recall macro": 0.7, "eval:f1 weighted": 0.7, "eval:precision weighted": 0.73, "eval:recall weighted": 0.69}, "post_train": {"ts": 1682539545.9636402, "eval:loss": 0.5922456979751587, "eval:acc": 0.8018018007278442, "eval:f1 micro": 0.81, "eval:precision micro": 0.85, "eval:recall micro": 0.77, "eval:f1 macro": 0.78, "eval:precision macro": 0.87, "eval:recall macro": 0.73, "eval:f1 weighted": 0.81, "eval:precision weighted": 0.87, "eval:recall weighted": 0.77}, "pre_update": {}, "post_update": {}}, {"round_no": 2, "pre_train": {"ts": 1682539567.8806713, "eval:loss": 0.8089703917503357, "eval:acc": 0.7747747898101807, "eval:f1 micro": 0.79, "eval:precision micro": 0.82, "eval:recall micro": 0.77, "eval:f1 macro": 0.8, "eval:precision macro": 0.86, "eval:recall macro": 0.78, "eval:f1 weighted": 0.78, "eval:precision weighted": 0.85, "eval:recall weighted": 0.77}, "post_train": {"ts": 1682539596.0198076, "eval:loss": 0.5872469544410706, "eval:acc": 0.8468468189239502, "eval:f1 micro": 0.83, "eval:precision micro": 0.86, "eval:recall micro": 0.81, "eval:f1 macro": 0.81, "eval:precision macro": 0.87, "eval:recall macro": 0.79, "eval:f1 weighted": 0.84, "eval:precision weighted": 0.88, "eval:recall weighted": 0.81}, "pre_update": {}, "post_update": {}}, {"round_no": 3, "pre_train": {"ts": 1682539618.437833, "eval:loss": 0.7567881941795349, "eval:acc": 0.8558558821678162, "eval:f1 micro": 0.85, "eval:precision micro": 0.87, "eval:recall micro": 0.83, "eval:f1 macro": 0.83, "eval:precision macro": 0.87, "eval:recall macro": 0.82, "eval:f1 weighted": 0.85, "eval:precision weighted": 0.89, "eval:recall weighted": 0.83}, "post_train": {"ts": 1682539644.5185692, "eval:loss": 0.5986435413360596, "eval:acc": 0.8468468189239502, "eval:f1 micro": 0.83, "eval:precision micro": 0.84, "eval:recall micro": 0.81, "eval:f1 macro": 0.81, "eval:precision macro": 0.85, "eval:recall macro": 0.78, "eval:f1 weighted": 0.83, "eval:precision weighted": 0.86, "eval:recall weighted": 0.81}, "pre_update": {}, "post_update": {}}, {"round_no": 4, "pre_train": {"ts": 1682539670.9291763, "eval:loss": 0.8227630257606506, "eval:acc": 0.8558558821678162, "eval:f1 micro": 0.86, "eval:precision micro": 0.87, "eval:recall micro": 0.85, "eval:f1 macro": 0.84, "eval:precision macro": 0.87, "eval:recall macro": 0.83, "eval:f1 weighted": 0.86, "eval:precision weighted": 0.88, "eval:recall weighted": 0.85}, "post_train": {"ts": 1682539695.1467643, "eval:loss": 0.5095996260643005, "eval:acc": 0.8648648858070374, "eval:f1 micro": 0.86, "eval:precision micro": 0.87, "eval:recall micro": 0.85, "eval:f1 macro": 0.84, "eval:precision macro": 0.88, "eval:recall macro": 0.83, "eval:f1 weighted": 0.86, "eval:precision weighted": 0.89, "eval:recall weighted": 0.85}, "pre_update": {}, "post_update": {}}, {"round_no": 5, "pre_train": {"ts": 1682539726.7491422, "eval:loss": 0.9384256601333618, "eval:acc": 0.8468468189239502, "eval:f1 micro": 0.84, "eval:precision micro": 0.85, "eval:recall micro": 0.84, "eval:f1 macro": 0.83, "eval:precision macro": 0.86, "eval:recall macro": 0.83, "eval:f1 weighted": 0.84, "eval:precision weighted": 0.87, "eval:recall weighted": 0.84}, "post_train": {"ts": 1682539754.131046, "eval:loss": 0.5360790491104126, "eval:acc": 0.8648648858070374, "eval:f1 micro": 0.86, "eval:precision micro": 0.87, "eval:recall micro": 0.85, "eval:f1 macro": 0.85, "eval:precision macro": 0.88, "eval:recall macro": 0.83, "eval:f1 weighted": 0.86, "eval:precision weighted": 0.89, "eval:recall weighted": 0.85}, "pre_update": {}, "post_update": {}}, {"round_no": 6, "pre_train": {"ts": 1682539780.4052377, "eval:loss": 0.9540181756019592, "eval:acc": 0.8288288116455078, "eval:f1 micro": 0.83, "eval:precision micro": 0.84, "eval:recall micro": 0.82, "eval:f1 macro": 0.82, "eval:precision macro": 0.85, "eval:recall macro": 0.81, "eval:f1 weighted": 0.83, "eval:precision weighted": 0.87, "eval:recall weighted": 0.82}, "post_train": {"ts": 1682539808.258693, "eval:loss": 0.5766754150390625, "eval:acc": 0.8828828930854797, "eval:f1 micro": 0.86, "eval:precision micro": 0.88, "eval:recall micro": 0.85, "eval:f1 macro": 0.85, "eval:precision macro": 0.9, "eval:recall macro": 0.83, "eval:f1 weighted": 0.87, "eval:precision weighted": 0.9, "eval:recall weighted": 0.85}, "pre_update": {}, "post_update": {}}, {"round_no": 7, "pre_train": {"ts": 1682539831.935914, "eval:loss": 0.8913524746894836, "eval:acc": 0.8558558821678162, "eval:f1 micro": 0.85, "eval:precision micro": 0.86, "eval:recall micro": 0.85, "eval:f1 macro": 0.84, "eval:precision macro": 0.87, "eval:recall macro": 0.83, "eval:f1 weighted": 0.86, "eval:precision weighted": 0.89, "eval:recall weighted": 0.85}, "post_train": {"ts": 1682539855.8586242, "eval:loss": 0.5244233012199402, "eval:acc": 0.8648648858070374, "eval:f1 micro": 0.86, "eval:precision micro": 0.88, "eval:recall micro": 0.84, "eval:f1 macro": 0.85, "eval:precision macro": 0.89, "eval:recall macro": 0.82, "eval:f1 weighted": 0.86, "eval:precision weighted": 0.9, "eval:recall weighted": 0.84}, "pre_update": {}, "post_update": {}}, {"round_no": 8, "pre_train": {"ts": 1682539884.9921424, "eval:loss": 0.9663966298103333, "eval:acc": 0.8558558821678162, "eval:f1 micro": 0.85, "eval:precision micro": 0.86, "eval:recall micro": 0.84, "eval:f1 macro": 0.83, "eval:precision macro": 0.86, "eval:recall macro": 0.83, "eval:f1 weighted": 0.85, "eval:precision weighted": 0.88, "eval:recall weighted": 0.84}, "post_train": {"ts": 1682539912.2411952, "eval:loss": 0.515075147151947, "eval:acc": 0.8828828930854797, "eval:f1 micro": 0.87, "eval:precision micro": 0.88, "eval:recall micro": 0.86, "eval:f1 macro": 0.87, "eval:precision macro": 0.89, "eval:recall macro": 0.85, "eval:f1 weighted": 0.87, "eval:precision weighted": 0.89, "eval:recall weighted": 0.86}, "pre_update": {}, "post_update": {}}, {"round_no": 9, "pre_train": {"ts": 1682539941.1732948, "eval:loss": 1.1601375341415405, "eval:acc": 0.8018018007278442, "eval:f1 micro": 0.81, "eval:precision micro": 0.81, "eval:recall micro": 0.8, "eval:f1 macro": 0.79, "eval:precision macro": 0.83, "eval:recall macro": 0.8, "eval:f1 weighted": 0.8, "eval:precision weighted": 0.84, "eval:recall weighted": 0.8}, "post_train": {"ts": 1682539967.6027038, "eval:loss": 0.5407336950302124, "eval:acc": 0.8738738894462585, "eval:f1 micro": 0.88, "eval:precision micro": 0.9, "eval:recall micro": 0.86, "eval:f1 macro": 0.89, "eval:precision macro": 0.91, "eval:recall macro": 0.88, "eval:f1 weighted": 0.88, "eval:precision weighted": 0.91, "eval:recall weighted": 0.86}, "pre_update": {}, "post_update": {}}, {"round_no": 10, "pre_train": {"ts": 1682539996.932291, "eval:loss": 1.1183230876922607, "eval:acc": 0.8468468189239502, "eval:f1 micro": 0.84, "eval:precision micro": 0.84, "eval:recall micro": 0.83, "eval:f1 macro": 0.81, "eval:precision macro": 0.85, "eval:recall macro": 0.83, "eval:f1 weighted": 0.83, "eval:precision weighted": 0.88, "eval:recall weighted": 0.83}, "post_train": {"ts": 1682540024.0986419, "eval:loss": 0.526921808719635, "eval:acc": 0.8738738894462585, "eval:f1 micro": 0.87, "eval:precision micro": 0.88, "eval:recall micro": 0.86, "eval:f1 macro": 0.85, "eval:precision macro": 0.89, "eval:recall macro": 0.84, "eval:f1 weighted": 0.87, "eval:precision weighted": 0.9, "eval:recall weighted": 0.86}, "pre_update": {}, "post_update": {}}, {"round_no": 11, "pre_train": {"ts": 1682540052.5839667, "eval:loss": 1.0837827920913696, "eval:acc": 0.8288288116455078, "eval:f1 micro": 0.83, "eval:precision micro": 0.83, "eval:recall micro": 0.83, "eval:f1 macro": 0.82, "eval:precision macro": 0.84, "eval:recall macro": 0.82, "eval:f1 weighted": 0.83, "eval:precision weighted": 0.86, "eval:recall weighted": 0.83}, "post_train": {"ts": 1682540078.4948995, "eval:loss": 0.5185651779174805, "eval:acc": 0.8648648858070374, "eval:f1 micro": 0.86, "eval:precision micro": 0.86, "eval:recall micro": 0.86, "eval:f1 macro": 0.87, "eval:precision macro": 0.88, "eval:recall macro": 0.86, "eval:f1 weighted": 0.86, "eval:precision weighted": 0.88, "eval:recall weighted": 0.86}, "pre_update": {}, "post_update": {}}, {"round_no": 12, "pre_train": {"ts": 1682540105.7629945, "eval:loss": 1.1547194719314575, "eval:acc": 0.8108108043670654, "eval:f1 micro": 0.82, "eval:precision micro": 0.83, "eval:recall micro": 0.81, "eval:f1 macro": 0.8, "eval:precision macro": 0.84, "eval:recall macro": 0.8, "eval:f1 weighted": 0.82, "eval:precision weighted": 0.86, "eval:recall weighted": 0.81}, "post_train": {"ts": 1682540132.0037918, "eval:loss": 0.5312259197235107, "eval:acc": 0.8738738894462585, "eval:f1 micro": 0.86, "eval:precision micro": 0.88, "eval:recall micro": 0.85, "eval:f1 macro": 0.87, "eval:precision macro": 0.89, "eval:recall macro": 0.86, "eval:f1 weighted": 0.86, "eval:precision weighted": 0.89, "eval:recall weighted": 0.85}, "pre_update": {}, "post_update": {}}, {"round_no": 13, "pre_train": {"ts": 1682540157.7975495, "eval:loss": 1.1728270053863525, "eval:acc": 0.8108108043670654, "eval:f1 micro": 0.81, "eval:precision micro": 0.82, "eval:recall micro": 0.81, "eval:f1 macro": 0.8, "eval:precision macro": 0.83, "eval:recall macro": 0.8, "eval:f1 weighted": 0.81, "eval:precision weighted": 0.85, "eval:recall weighted": 0.81}, "post_train": {"ts": 1682540185.0233626, "eval:loss": 0.5476779937744141, "eval:acc": 0.8558558821678162, "eval:f1 micro": 0.85, "eval:precision micro": 0.87, "eval:recall micro": 0.83, "eval:f1 macro": 0.84, "eval:precision macro": 0.88, "eval:recall macro": 0.81, "eval:f1 weighted": 0.85, "eval:precision weighted": 0.89, "eval:recall weighted": 0.83}, "pre_update": {}, "post_update": {}}, {"round_no": 14, "pre_train": {"ts": 1682540208.8035293, "eval:loss": 1.2300163507461548, "eval:acc": 0.8198198080062866, "eval:f1 micro": 0.81, "eval:precision micro": 0.82, "eval:recall micro": 0.81, "eval:f1 macro": 0.8, "eval:precision macro": 0.83, "eval:recall macro": 0.81, "eval:f1 weighted": 0.81, "eval:precision weighted": 0.85, "eval:recall weighted": 0.81}, "post_train": {"ts": 1682540235.765978, "eval:loss": 0.4914105534553528, "eval:acc": 0.8918918967247009, "eval:f1 micro": 0.88, "eval:precision micro": 0.9, "eval:recall micro": 0.86, "eval:f1 macro": 0.88, "eval:precision macro": 0.91, "eval:recall macro": 0.87, "eval:f1 weighted": 0.88, "eval:precision weighted": 0.91, "eval:recall weighted": 0.86}, "pre_update": {}, "post_update": {}}, {"round_no": 15, "pre_train": {"ts": 1682540264.7138138, "eval:loss": 1.1855429410934448, "eval:acc": 0.837837815284729, "eval:f1 micro": 0.84, "eval:precision micro": 0.85, "eval:recall micro": 0.84, "eval:f1 macro": 0.82, "eval:precision macro": 0.85, "eval:recall macro": 0.83, "eval:f1 weighted": 0.84, "eval:precision weighted": 0.87, "eval:recall weighted": 0.84}, "post_train": {"ts": 1682540291.0482383, "eval:loss": 0.5555059313774109, "eval:acc": 0.8918918967247009, "eval:f1 micro": 0.88, "eval:precision micro": 0.89, "eval:recall micro": 0.86, "eval:f1 macro": 0.88, "eval:precision macro": 0.9, "eval:recall macro": 0.86, "eval:f1 weighted": 0.88, "eval:precision weighted": 0.91, "eval:recall weighted": 0.86}, "pre_update": {}, "post_update": {}}, {"round_no": 16, "pre_train": {"ts": 1682540311.8206863, "eval:loss": 1.1434648036956787, "eval:acc": 0.837837815284729, "eval:f1 micro": 0.84, "eval:precision micro": 0.85, "eval:recall micro": 0.84, "eval:f1 macro": 0.83, "eval:precision macro": 0.85, "eval:recall macro": 0.83, "eval:f1 weighted": 0.84, "eval:precision weighted": 0.87, "eval:recall weighted": 0.84}, "post_train": {"ts": 1682540329.9904597, "eval:loss": 0.5685794353485107, "eval:acc": 0.8738738894462585, "eval:f1 micro": 0.87, "eval:precision micro": 0.89, "eval:recall micro": 0.86, "eval:f1 macro": 0.86, "eval:precision macro": 0.9, "eval:recall macro": 0.84, "eval:f1 weighted": 0.87, "eval:precision weighted": 0.9, "eval:recall weighted": 0.86}, "pre_update": {}, "post_update": {}}, {"round_no": 17, "pre_train": {"ts": 1682540371.479753, "eval:loss": 1.16951584815979, "eval:acc": 0.8198198080062866, "eval:f1 micro": 0.81, "eval:precision micro": 0.82, "eval:recall micro": 0.81, "eval:f1 macro": 0.8, "eval:precision macro": 0.83, "eval:recall macro": 0.8, "eval:f1 weighted": 0.81, "eval:precision weighted": 0.85, "eval:recall weighted": 0.81}, "post_train": {"ts": 1682540397.1525216, "eval:loss": 0.6047326326370239, "eval:acc": 0.8648648858070374, "eval:f1 micro": 0.87, "eval:precision micro": 0.88, "eval:recall micro": 0.86, "eval:f1 macro": 0.87, "eval:precision macro": 0.89, "eval:recall macro": 0.86, "eval:f1 weighted": 0.87, "eval:precision weighted": 0.9, "eval:recall weighted": 0.86}, "pre_update": {}, "post_update": {}}, {"round_no": 18, "pre_train": {"ts": 1682540417.7945673, "eval:loss": 1.2625945806503296, "eval:acc": 0.8198198080062866, "eval:f1 micro": 0.83, "eval:precision micro": 0.83, "eval:recall micro": 0.82, "eval:f1 macro": 0.82, "eval:precision macro": 0.86, "eval:recall macro": 0.81, "eval:f1 weighted": 0.82, "eval:precision weighted": 0.86, "eval:recall weighted": 0.82}, "post_train": {"ts": 1682540438.0055745, "eval:loss": 0.6302154064178467, "eval:acc": 0.8648648858070374, "eval:f1 micro": 0.86, "eval:precision micro": 0.87, "eval:recall micro": 0.85, "eval:f1 macro": 0.86, "eval:precision macro": 0.89, "eval:recall macro": 0.86, "eval:f1 weighted": 0.86, "eval:precision weighted": 0.9, "eval:recall weighted": 0.85}, "pre_update": {}, "post_update": {}}, {"round_no": 19, "pre_train": {"ts": 1682540479.2329361, "eval:loss": 1.5365512371063232, "eval:acc": 0.8018018007278442, "eval:f1 micro": 0.8, "eval:precision micro": 0.8, "eval:recall micro": 0.79, "eval:f1 macro": 0.78, "eval:precision macro": 0.83, "eval:recall macro": 0.79, "eval:f1 weighted": 0.78, "eval:precision weighted": 0.84, "eval:recall weighted": 0.79}, "post_train": {"ts": 1682540505.4965587, "eval:loss": 0.5511663556098938, "eval:acc": 0.8738738894462585, "eval:f1 micro": 0.87, "eval:precision micro": 0.89, "eval:recall micro": 0.86, "eval:f1 macro": 0.86, "eval:precision macro": 0.9, "eval:recall macro": 0.84, "eval:f1 weighted": 0.87, "eval:precision weighted": 0.9, "eval:recall weighted": 0.86}, "pre_update": {}, "post_update": {}}]
