[{"round_no": 0, "pre_train": {"ts": 1682539456.2311656}, "post_train": {"ts": 1682539493.029003, "eval:loss": 0.7038654088973999, "eval:acc": 0.792792797088623, "eval:f1 micro": 0.77, "eval:precision micro": 0.9, "eval:recall micro": 0.68, "eval:f1 macro": 0.65, "eval:precision macro": 0.75, "eval:recall macro": 0.6, "eval:f1 weighted": 0.72, "eval:precision weighted": 0.81, "eval:recall weighted": 0.68}, "pre_update": {}, "post_update": {}}, {"round_no": 1, "pre_train": {"ts": 1682539519.8951848, "eval:loss": 0.6939691305160522, "eval:acc": 0.7837837934494019, "eval:f1 micro": 0.8, "eval:precision micro": 0.84, "eval:recall micro": 0.76, "eval:f1 macro": 0.66, "eval:precision macro": 0.77, "eval:recall macro": 0.63, "eval:f1 weighted": 0.78, "eval:precision weighted": 0.87, "eval:recall weighted": 0.76}, "post_train": {"ts": 1682539546.2728343, "eval:loss": 0.4964951276779175, "eval:acc": 0.8828828930854797, "eval:f1 micro": 0.88, "eval:precision micro": 0.91, "eval:recall micro": 0.86, "eval:f1 macro": 0.78, "eval:precision macro": 0.83, "eval:recall macro": 0.75, "eval:f1 weighted": 0.88, "eval:precision weighted": 0.93, "eval:recall weighted": 0.86}, "pre_update": {}, "post_update": {}}, {"round_no": 2, "pre_train": {"ts": 1682539572.58209, "eval:loss": 0.6687316298484802, "eval:acc": 0.8468468189239502, "eval:f1 micro": 0.84, "eval:precision micro": 0.87, "eval:recall micro": 0.82, "eval:f1 macro": 0.74, "eval:precision macro": 0.8, "eval:recall macro": 0.71, "eval:f1 weighted": 0.84, "eval:precision weighted": 0.9, "eval:recall weighted": 0.82}, "post_train": {"ts": 1682539598.3780625, "eval:loss": 0.47453489899635315, "eval:acc": 0.8828828930854797, "eval:f1 micro": 0.9, "eval:precision micro": 0.92, "eval:recall micro": 0.87, "eval:f1 macro": 0.8, "eval:precision macro": 0.85, "eval:recall macro": 0.78, "eval:f1 weighted": 0.9, "eval:precision weighted": 0.94, "eval:recall weighted": 0.87}, "pre_update": {}, "post_update": {}}, {"round_no": 3, "pre_train": {"ts": 1682539617.2066674, "eval:loss": 0.6091610193252563, "eval:acc": 0.8648648858070374, "eval:f1 micro": 0.88, "eval:precision micro": 0.89, "eval:recall micro": 0.86, "eval:f1 macro": 0.78, "eval:precision macro": 0.8, "eval:recall macro": 0.77, "eval:f1 weighted": 0.88, "eval:precision weighted": 0.89, "eval:recall weighted": 0.86}, "post_train": {"ts": 1682539641.045349, "eval:loss": 0.42950522899627686, "eval:acc": 0.8918918967247009, "eval:f1 micro": 0.89, "eval:precision micro": 0.91, "eval:recall micro": 0.88, "eval:f1 macro": 0.8, "eval:precision macro": 0.83, "eval:recall macro": 0.78, "eval:f1 weighted": 0.9, "eval:precision weighted": 0.92, "eval:recall weighted": 0.88}, "pre_update": {}, "post_update": {}}, {"round_no": 4, "pre_train": {"ts": 1682539677.7339053, "eval:loss": 0.6817774176597595, "eval:acc": 0.8828828930854797, "eval:f1 micro": 0.88, "eval:precision micro": 0.89, "eval:recall micro": 0.87, "eval:f1 macro": 0.79, "eval:precision macro": 0.8, "eval:recall macro": 0.78, "eval:f1 weighted": 0.88, "eval:precision weighted": 0.89, "eval:recall weighted": 0.87}, "post_train": {"ts": 1682539703.0965536, "eval:loss": 0.4673090875148773, "eval:acc": 0.8918918967247009, "eval:f1 micro": 0.88, "eval:precision micro": 0.91, "eval:recall micro": 0.86, "eval:f1 macro": 0.79, "eval:precision macro": 0.84, "eval:recall macro": 0.76, "eval:f1 weighted": 0.88, "eval:precision weighted": 0.92, "eval:recall weighted": 0.86}, "pre_update": {}, "post_update": {}}, {"round_no": 5, "pre_train": {"ts": 1682539731.4428897, "eval:loss": 0.7312068939208984, "eval:acc": 0.8828828930854797, "eval:f1 micro": 0.89, "eval:precision micro": 0.9, "eval:recall micro": 0.88, "eval:f1 macro": 0.8, "eval:precision macro": 0.81, "eval:recall macro": 0.78, "eval:f1 weighted": 0.89, "eval:precision weighted": 0.9, "eval:recall weighted": 0.88}, "post_train": {"ts": 1682539757.2955794, "eval:loss": 0.4539982080459595, "eval:acc": 0.8918918967247009, "eval:f1 micro": 0.89, "eval:precision micro": 0.91, "eval:recall micro": 0.88, "eval:f1 macro": 0.81, "eval:precision macro": 0.84, "eval:recall macro": 0.78, "eval:f1 weighted": 0.9, "eval:precision weighted": 0.93, "eval:recall weighted": 0.88}, "pre_update": {}, "post_update": {}}, {"round_no": 6, "pre_train": {"ts": 1682539779.1012585, "eval:loss": 0.7441878914833069, "eval:acc": 0.8918918967247009, "eval:f1 micro": 0.9, "eval:precision micro": 0.9, "eval:recall micro": 0.89, "eval:f1 macro": 0.8, "eval:precision macro": 0.81, "eval:recall macro": 0.8, "eval:f1 weighted": 0.89, "eval:precision weighted": 0.9, "eval:recall weighted": 0.89}, "post_train": {"ts": 1682539804.4124153, "eval:loss": 0.4783657193183899, "eval:acc": 0.9009009003639221, "eval:f1 micro": 0.9, "eval:precision micro": 0.91, "eval:recall micro": 0.89, "eval:f1 macro": 0.81, "eval:precision macro": 0.82, "eval:recall macro": 0.8, "eval:f1 weighted": 0.9, "eval:precision weighted": 0.91, "eval:recall weighted": 0.89}, "pre_update": {}, "post_update": {}}, {"round_no": 7, "pre_train": {"ts": 1682539831.5154324, "eval:loss": 0.7223433256149292, "eval:acc": 0.8828828930854797, "eval:f1 micro": 0.89, "eval:precision micro": 0.89, "eval:recall micro": 0.88, "eval:f1 macro": 0.79, "eval:precision macro": 0.8, "eval:recall macro": 0.79, "eval:f1 weighted": 0.89, "eval:precision weighted": 0.89, "eval:recall weighted": 0.88}, "post_train": {"ts": 1682539853.5394795, "eval:loss": 0.4165443480014801, "eval:acc": 0.8828828930854797, "eval:f1 micro": 0.9, "eval:precision micro": 0.92, "eval:recall micro": 0.88, "eval:f1 macro": 0.81, "eval:precision macro": 0.85, "eval:recall macro": 0.78, "eval:f1 weighted": 0.9, "eval:precision weighted": 0.93, "eval:recall weighted": 0.88}, "pre_update": {}, "post_update": {}}, {"round_no": 8, "pre_train": {"ts": 1682539885.2756512, "eval:loss": 0.7165003418922424, "eval:acc": 0.8828828930854797, "eval:f1 micro": 0.88, "eval:precision micro": 0.88, "eval:recall micro": 0.88, "eval:f1 macro": 0.79, "eval:precision macro": 0.8, "eval:recall macro": 0.79, "eval:f1 weighted": 0.88, "eval:precision weighted": 0.89, "eval:recall weighted": 0.88}, "post_train": {"ts": 1682539913.1396377, "eval:loss": 0.4119921028614044, "eval:acc": 0.9009009003639221, "eval:f1 micro": 0.9, "eval:precision micro": 0.92, "eval:recall micro": 0.88, "eval:f1 macro": 0.81, "eval:precision macro": 0.84, "eval:recall macro": 0.79, "eval:f1 weighted": 0.9, "eval:precision weighted": 0.93, "eval:recall weighted": 0.88}, "pre_update": {}, "post_update": {}}, {"round_no": 9, "pre_train": {"ts": 1682539944.494656, "eval:loss": 0.8773326277732849, "eval:acc": 0.8828828930854797, "eval:f1 micro": 0.89, "eval:precision micro": 0.9, "eval:recall micro": 0.87, "eval:f1 macro": 0.79, "eval:precision macro": 0.81, "eval:recall macro": 0.78, "eval:f1 weighted": 0.88, "eval:precision weighted": 0.9, "eval:recall weighted": 0.87}, "post_train": {"ts": 1682539970.4715836, "eval:loss": 0.4560471475124359, "eval:acc": 0.8918918967247009, "eval:f1 micro": 0.89, "eval:precision micro": 0.89, "eval:recall micro": 0.88, "eval:f1 macro": 0.79, "eval:precision macro": 0.82, "eval:recall macro": 0.78, "eval:f1 weighted": 0.89, "eval:precision weighted": 0.9, "eval:recall weighted": 0.88}, "pre_update": {}, "post_update": {}}, {"round_no": 10, "pre_train": {"ts": 1682539997.9941747, "eval:loss": 0.8405052423477173, "eval:acc": 0.8918918967247009, "eval:f1 micro": 0.9, "eval:precision micro": 0.9, "eval:recall micro": 0.89, "eval:f1 macro": 0.8, "eval:precision macro": 0.81, "eval:recall macro": 0.8, "eval:f1 weighted": 0.89, "eval:precision weighted": 0.9, "eval:recall weighted": 0.89}, "post_train": {"ts": 1682540024.4180045, "eval:loss": 0.48056232929229736, "eval:acc": 0.8738738894462585, "eval:f1 micro": 0.88, "eval:precision micro": 0.89, "eval:recall micro": 0.87, "eval:f1 macro": 0.79, "eval:precision macro": 0.82, "eval:recall macro": 0.77, "eval:f1 weighted": 0.88, "eval:precision weighted": 0.9, "eval:recall weighted": 0.87}, "pre_update": {}, "post_update": {}}, {"round_no": 11, "pre_train": {"ts": 1682540049.6206858, "eval:loss": 0.8925220966339111, "eval:acc": 0.9009009003639221, "eval:f1 micro": 0.9, "eval:precision micro": 0.9, "eval:recall micro": 0.89, "eval:f1 macro": 0.8, "eval:precision macro": 0.81, "eval:recall macro": 0.8, "eval:f1 weighted": 0.89, "eval:precision weighted": 0.9, "eval:recall weighted": 0.89}, "post_train": {"ts": 1682540077.1466615, "eval:loss": 0.4547169804573059, "eval:acc": 0.8828828930854797, "eval:f1 micro": 0.89, "eval:precision micro": 0.89, "eval:recall micro": 0.88, "eval:f1 macro": 0.79, "eval:precision macro": 0.82, "eval:recall macro": 0.78, "eval:f1 weighted": 0.89, "eval:precision weighted": 0.9, "eval:recall weighted": 0.88}, "pre_update": {}, "post_update": {}}, {"round_no": 12, "pre_train": {"ts": 1682540103.5485523, "eval:loss": 0.9243981838226318, "eval:acc": 0.8738738894462585, "eval:f1 micro": 0.87, "eval:precision micro": 0.87, "eval:recall micro": 0.87, "eval:f1 macro": 0.78, "eval:precision macro": 0.79, "eval:recall macro": 0.78, "eval:f1 weighted": 0.87, "eval:precision weighted": 0.88, "eval:recall weighted": 0.87}, "post_train": {"ts": 1682540130.2772324, "eval:loss": 0.5053110122680664, "eval:acc": 0.8918918967247009, "eval:f1 micro": 0.89, "eval:precision micro": 0.89, "eval:recall micro": 0.88, "eval:f1 macro": 0.8, "eval:precision macro": 0.83, "eval:recall macro": 0.78, "eval:f1 weighted": 0.89, "eval:precision weighted": 0.91, "eval:recall weighted": 0.88}, "pre_update": {}, "post_update": {}}, {"round_no": 13, "pre_train": {"ts": 1682540159.0980155, "eval:loss": 0.9241365790367126, "eval:acc": 0.8918918967247009, "eval:f1 micro": 0.89, "eval:precision micro": 0.89, "eval:recall micro": 0.89, "eval:f1 macro": 0.8, "eval:precision macro": 0.8, "eval:recall macro": 0.8, "eval:f1 weighted": 0.89, "eval:precision weighted": 0.89, "eval:recall weighted": 0.89}, "post_train": {"ts": 1682540185.4185863, "eval:loss": 0.4988153874874115, "eval:acc": 0.8918918967247009, "eval:f1 micro": 0.89, "eval:precision micro": 0.89, "eval:recall micro": 0.89, "eval:f1 macro": 0.8, "eval:precision macro": 0.82, "eval:recall macro": 0.78, "eval:f1 weighted": 0.89, "eval:precision weighted": 0.9, "eval:recall weighted": 0.89}, "pre_update": {}, "post_update": {}}, {"round_no": 14, "pre_train": {"ts": 1682540211.2316675, "eval:loss": 0.9482285976409912, "eval:acc": 0.8828828930854797, "eval:f1 micro": 0.89, "eval:precision micro": 0.89, "eval:recall micro": 0.88, "eval:f1 macro": 0.79, "eval:precision macro": 0.81, "eval:recall macro": 0.78, "eval:f1 weighted": 0.89, "eval:precision weighted": 0.9, "eval:recall weighted": 0.88}, "post_train": {"ts": 1682540238.3504183, "eval:loss": 0.5263527035713196, "eval:acc": 0.8918918967247009, "eval:f1 micro": 0.88, "eval:precision micro": 0.9, "eval:recall micro": 0.86, "eval:f1 macro": 0.78, "eval:precision macro": 0.83, "eval:recall macro": 0.75, "eval:f1 weighted": 0.88, "eval:precision weighted": 0.91, "eval:recall weighted": 0.86}, "pre_update": {}, "post_update": {}}, {"round_no": 15, "pre_train": {"ts": 1682540257.9330587, "eval:loss": 0.9137653112411499, "eval:acc": 0.8918918967247009, "eval:f1 micro": 0.9, "eval:precision micro": 0.9, "eval:recall micro": 0.89, "eval:f1 macro": 0.8, "eval:precision macro": 0.81, "eval:recall macro": 0.8, "eval:f1 weighted": 0.9, "eval:precision weighted": 0.9, "eval:recall weighted": 0.89}, "post_train": {"ts": 1682540276.5494034, "eval:loss": 0.4586069881916046, "eval:acc": 0.8828828930854797, "eval:f1 micro": 0.89, "eval:precision micro": 0.9, "eval:recall micro": 0.88, "eval:f1 macro": 0.8, "eval:precision macro": 0.83, "eval:recall macro": 0.78, "eval:f1 weighted": 0.89, "eval:precision weighted": 0.91, "eval:recall weighted": 0.88}, "pre_update": {}, "post_update": {}}, {"round_no": 16, "pre_train": {"ts": 1682540317.1866102, "eval:loss": 0.9018109440803528, "eval:acc": 0.8918918967247009, "eval:f1 micro": 0.89, "eval:precision micro": 0.89, "eval:recall micro": 0.88, "eval:f1 macro": 0.8, "eval:precision macro": 0.81, "eval:recall macro": 0.79, "eval:f1 weighted": 0.89, "eval:precision weighted": 0.9, "eval:recall weighted": 0.88}, "post_train": {"ts": 1682540344.6159565, "eval:loss": 0.4766606092453003, "eval:acc": 0.8828828930854797, "eval:f1 micro": 0.87, "eval:precision micro": 0.89, "eval:recall micro": 0.86, "eval:f1 macro": 0.78, "eval:precision macro": 0.82, "eval:recall macro": 0.75, "eval:f1 weighted": 0.87, "eval:precision weighted": 0.9, "eval:recall weighted": 0.86}, "pre_update": {}, "post_update": {}}, {"round_no": 17, "pre_train": {"ts": 1682540370.6184592, "eval:loss": 0.9621466398239136, "eval:acc": 0.8738738894462585, "eval:f1 micro": 0.87, "eval:precision micro": 0.87, "eval:recall micro": 0.87, "eval:f1 macro": 0.78, "eval:precision macro": 0.8, "eval:recall macro": 0.78, "eval:f1 weighted": 0.87, "eval:precision weighted": 0.88, "eval:recall weighted": 0.87}, "post_train": {"ts": 1682540396.4605768, "eval:loss": 0.498421847820282, "eval:acc": 0.9009009003639221, "eval:f1 micro": 0.89, "eval:precision micro": 0.91, "eval:recall micro": 0.88, "eval:f1 macro": 0.8, "eval:precision macro": 0.83, "eval:recall macro": 0.78, "eval:f1 weighted": 0.89, "eval:precision weighted": 0.91, "eval:recall weighted": 0.88}, "pre_update": {}, "post_update": {}}, {"round_no": 18, "pre_train": {"ts": 1682540418.1819406, "eval:loss": 0.9145361185073853, "eval:acc": 0.8648648858070374, "eval:f1 micro": 0.86, "eval:precision micro": 0.86, "eval:recall micro": 0.86, "eval:f1 macro": 0.77, "eval:precision macro": 0.78, "eval:recall macro": 0.77, "eval:f1 weighted": 0.86, "eval:precision weighted": 0.86, "eval:recall weighted": 0.86}, "post_train": {"ts": 1682540439.7232513, "eval:loss": 0.46377646923065186, "eval:acc": 0.8828828930854797, "eval:f1 micro": 0.88, "eval:precision micro": 0.89, "eval:recall micro": 0.87, "eval:f1 macro": 0.79, "eval:precision macro": 0.82, "eval:recall macro": 0.78, "eval:f1 weighted": 0.88, "eval:precision weighted": 0.9, "eval:recall weighted": 0.87}, "pre_update": {}, "post_update": {}}, {"round_no": 19, "pre_train": {"ts": 1682540472.9710345, "eval:loss": 1.0417041778564453, "eval:acc": 0.8648648858070374, "eval:f1 micro": 0.87, "eval:precision micro": 0.87, "eval:recall micro": 0.86, "eval:f1 macro": 0.76, "eval:precision macro": 0.79, "eval:recall macro": 0.75, "eval:f1 weighted": 0.86, "eval:precision weighted": 0.88, "eval:recall weighted": 0.86}, "post_train": {"ts": 1682540498.916587, "eval:loss": 0.4450768828392029, "eval:acc": 0.9099099040031433, "eval:f1 micro": 0.9, "eval:precision micro": 0.92, "eval:recall micro": 0.88, "eval:f1 macro": 0.81, "eval:precision macro": 0.84, "eval:recall macro": 0.78, "eval:f1 weighted": 0.9, "eval:precision weighted": 0.92, "eval:recall weighted": 0.88}, "pre_update": {}, "post_update": {}}]
