[{"round_no": 0, "pre_train": {"ts": 1682537758.9961169}, "post_train": {"ts": 1682537795.8624382, "eval:loss": 0.8071845173835754, "eval:acc": 0.7387387156486511, "eval:f1 micro": 0.72, "eval:precision micro": 0.8, "eval:recall micro": 0.66, "eval:f1 macro": 0.6, "eval:precision macro": 0.71, "eval:recall macro": 0.59, "eval:f1 weighted": 0.65, "eval:precision weighted": 0.73, "eval:recall weighted": 0.66}, "pre_update": {}, "post_update": {}}, {"round_no": 1, "pre_train": {"ts": 1682537815.4971423, "eval:loss": 0.5334440469741821, "eval:acc": 0.8918918967247009, "eval:f1 micro": 0.85, "eval:precision micro": 0.99, "eval:recall micro": 0.75, "eval:f1 macro": 0.8, "eval:precision macro": 0.99, "eval:recall macro": 0.7, "eval:f1 weighted": 0.83, "eval:precision weighted": 0.99, "eval:recall weighted": 0.75}, "post_train": {"ts": 1682537843.6264312, "eval:loss": 0.37362903356552124, "eval:acc": 0.8648648858070374, "eval:f1 micro": 0.87, "eval:precision micro": 0.9, "eval:recall micro": 0.85, "eval:f1 macro": 0.84, "eval:precision macro": 0.92, "eval:recall macro": 0.83, "eval:f1 weighted": 0.86, "eval:precision weighted": 0.91, "eval:recall weighted": 0.85}, "pre_update": {}, "post_update": {}}, {"round_no": 2, "pre_train": {"ts": 1682537858.238524, "eval:loss": 0.2365114390850067, "eval:acc": 0.9459459185600281, "eval:f1 micro": 0.95, "eval:precision micro": 0.99, "eval:recall micro": 0.92, "eval:f1 macro": 0.94, "eval:precision macro": 0.98, "eval:recall macro": 0.92, "eval:f1 weighted": 0.95, "eval:precision weighted": 0.99, "eval:recall weighted": 0.92}, "post_train": {"ts": 1682537886.3057714, "eval:loss": 0.2421884685754776, "eval:acc": 0.9009009003639221, "eval:f1 micro": 0.9, "eval:precision micro": 0.92, "eval:recall micro": 0.89, "eval:f1 macro": 0.88, "eval:precision macro": 0.91, "eval:recall macro": 0.88, "eval:f1 weighted": 0.9, "eval:precision weighted": 0.92, "eval:recall weighted": 0.89}, "pre_update": {}, "post_update": {}}, {"round_no": 3, "pre_train": {"ts": 1682537900.7273843, "eval:loss": 0.17311033606529236, "eval:acc": 0.9459459185600281, "eval:f1 micro": 0.95, "eval:precision micro": 0.96, "eval:recall micro": 0.95, "eval:f1 macro": 0.95, "eval:precision macro": 0.96, "eval:recall macro": 0.95, "eval:f1 weighted": 0.95, "eval:precision weighted": 0.97, "eval:recall weighted": 0.95}, "post_train": {"ts": 1682537927.6400294, "eval:loss": 0.15169325470924377, "eval:acc": 0.9459459185600281, "eval:f1 micro": 0.94, "eval:precision micro": 0.95, "eval:recall micro": 0.93, "eval:f1 macro": 0.93, "eval:precision macro": 0.96, "eval:recall macro": 0.91, "eval:f1 weighted": 0.94, "eval:precision weighted": 0.96, "eval:recall weighted": 0.93}, "pre_update": {}, "post_update": {}}, {"round_no": 4, "pre_train": {"ts": 1682537938.2781136, "eval:loss": 0.14419229328632355, "eval:acc": 0.954954981803894, "eval:f1 micro": 0.96, "eval:precision micro": 0.96, "eval:recall micro": 0.95, "eval:f1 macro": 0.96, "eval:precision macro": 0.96, "eval:recall macro": 0.96, "eval:f1 weighted": 0.96, "eval:precision weighted": 0.97, "eval:recall weighted": 0.95}, "post_train": {"ts": 1682537967.1619337, "eval:loss": 0.17964978516101837, "eval:acc": 0.9279279112815857, "eval:f1 micro": 0.93, "eval:precision micro": 0.94, "eval:recall micro": 0.93, "eval:f1 macro": 0.93, "eval:precision macro": 0.95, "eval:recall macro": 0.92, "eval:f1 weighted": 0.93, "eval:precision weighted": 0.94, "eval:recall weighted": 0.93}, "pre_update": {}, "post_update": {}}, {"round_no": 5, "pre_train": {"ts": 1682537979.4977772, "eval:loss": 0.12444954365491867, "eval:acc": 0.954954981803894, "eval:f1 micro": 0.95, "eval:precision micro": 0.95, "eval:recall micro": 0.95, "eval:f1 macro": 0.95, "eval:precision macro": 0.95, "eval:recall macro": 0.96, "eval:f1 weighted": 0.95, "eval:precision weighted": 0.96, "eval:recall weighted": 0.95}, "post_train": {"ts": 1682538008.3678558, "eval:loss": 0.13749079406261444, "eval:acc": 0.9369369149208069, "eval:f1 micro": 0.94, "eval:precision micro": 0.95, "eval:recall micro": 0.94, "eval:f1 macro": 0.94, "eval:precision macro": 0.95, "eval:recall macro": 0.93, "eval:f1 weighted": 0.94, "eval:precision weighted": 0.95, "eval:recall weighted": 0.94}, "pre_update": {}, "post_update": {}}, {"round_no": 6, "pre_train": {"ts": 1682538023.332354, "eval:loss": 0.11805061995983124, "eval:acc": 0.954954981803894, "eval:f1 micro": 0.95, "eval:precision micro": 0.95, "eval:recall micro": 0.95, "eval:f1 macro": 0.95, "eval:precision macro": 0.95, "eval:recall macro": 0.96, "eval:f1 weighted": 0.95, "eval:precision weighted": 0.96, "eval:recall weighted": 0.95}, "post_train": {"ts": 1682538050.7404664, "eval:loss": 0.1026739850640297, "eval:acc": 0.954954981803894, "eval:f1 micro": 0.96, "eval:precision micro": 0.96, "eval:recall micro": 0.95, "eval:f1 macro": 0.96, "eval:precision macro": 0.97, "eval:recall macro": 0.95, "eval:f1 weighted": 0.96, "eval:precision weighted": 0.96, "eval:recall weighted": 0.95}, "pre_update": {}, "post_update": {}}, {"round_no": 7, "pre_train": {"ts": 1682538064.9343832, "eval:loss": 0.10723810642957687, "eval:acc": 0.954954981803894, "eval:f1 micro": 0.95, "eval:precision micro": 0.95, "eval:recall micro": 0.95, "eval:f1 macro": 0.95, "eval:precision macro": 0.95, "eval:recall macro": 0.96, "eval:f1 weighted": 0.95, "eval:precision weighted": 0.96, "eval:recall weighted": 0.95}, "post_train": {"ts": 1682538092.0128853, "eval:loss": 0.09982417523860931, "eval:acc": 0.9729729890823364, "eval:f1 micro": 0.97, "eval:precision micro": 0.97, "eval:recall micro": 0.97, "eval:f1 macro": 0.97, "eval:precision macro": 0.98, "eval:recall macro": 0.97, "eval:f1 weighted": 0.97, "eval:precision weighted": 0.97, "eval:recall weighted": 0.97}, "pre_update": {}, "post_update": {}}, {"round_no": 8, "pre_train": {"ts": 1682538104.5245929, "eval:loss": 0.09920372813940048, "eval:acc": 0.954954981803894, "eval:f1 micro": 0.95, "eval:precision micro": 0.95, "eval:recall micro": 0.95, "eval:f1 macro": 0.95, "eval:precision macro": 0.95, "eval:recall macro": 0.96, "eval:f1 weighted": 0.95, "eval:precision weighted": 0.96, "eval:recall weighted": 0.95}, "post_train": {"ts": 1682538132.1534796, "eval:loss": 0.09914057701826096, "eval:acc": 0.9459459185600281, "eval:f1 micro": 0.95, "eval:precision micro": 0.95, "eval:recall micro": 0.95, "eval:f1 macro": 0.95, "eval:precision macro": 0.96, "eval:recall macro": 0.94, "eval:f1 weighted": 0.95, "eval:precision weighted": 0.96, "eval:recall weighted": 0.95}, "pre_update": {}, "post_update": {}}, {"round_no": 9, "pre_train": {"ts": 1682538144.0405812, "eval:loss": 0.09889331459999084, "eval:acc": 0.954954981803894, "eval:f1 micro": 0.95, "eval:precision micro": 0.95, "eval:recall micro": 0.95, "eval:f1 macro": 0.95, "eval:precision macro": 0.95, "eval:recall macro": 0.96, "eval:f1 weighted": 0.95, "eval:precision weighted": 0.96, "eval:recall weighted": 0.95}, "post_train": {"ts": 1682538172.842519, "eval:loss": 0.13265737891197205, "eval:acc": 0.954954981803894, "eval:f1 micro": 0.96, "eval:precision micro": 0.96, "eval:recall micro": 0.95, "eval:f1 macro": 0.95, "eval:precision macro": 0.97, "eval:recall macro": 0.95, "eval:f1 weighted": 0.96, "eval:precision weighted": 0.97, "eval:recall weighted": 0.95}, "pre_update": {}, "post_update": {}}, {"round_no": 10, "pre_train": {"ts": 1682538184.9947476, "eval:loss": 0.09210442006587982, "eval:acc": 0.954954981803894, "eval:f1 micro": 0.95, "eval:precision micro": 0.95, "eval:recall micro": 0.95, "eval:f1 macro": 0.95, "eval:precision macro": 0.95, "eval:recall macro": 0.96, "eval:f1 weighted": 0.95, "eval:precision weighted": 0.96, "eval:recall weighted": 0.95}, "post_train": {"ts": 1682538213.3232229, "eval:loss": 0.10656119138002396, "eval:acc": 0.9729729890823364, "eval:f1 micro": 0.97, "eval:precision micro": 0.98, "eval:recall micro": 0.96, "eval:f1 macro": 0.97, "eval:precision macro": 0.98, "eval:recall macro": 0.97, "eval:f1 weighted": 0.97, "eval:precision weighted": 0.98, "eval:recall weighted": 0.96}, "pre_update": {}, "post_update": {}}, {"round_no": 11, "pre_train": {"ts": 1682538227.195124, "eval:loss": 0.08422379940748215, "eval:acc": 0.954954981803894, "eval:f1 micro": 0.95, "eval:precision micro": 0.95, "eval:recall micro": 0.95, "eval:f1 macro": 0.95, "eval:precision macro": 0.95, "eval:recall macro": 0.96, "eval:f1 weighted": 0.95, "eval:precision weighted": 0.96, "eval:recall weighted": 0.95}, "post_train": {"ts": 1682538255.5974312, "eval:loss": 0.11745038628578186, "eval:acc": 0.9639639854431152, "eval:f1 micro": 0.96, "eval:precision micro": 0.96, "eval:recall micro": 0.96, "eval:f1 macro": 0.96, "eval:precision macro": 0.97, "eval:recall macro": 0.96, "eval:f1 weighted": 0.96, "eval:precision weighted": 0.97, "eval:recall weighted": 0.96}, "pre_update": {}, "post_update": {}}, {"round_no": 12, "pre_train": {"ts": 1682538267.7092426, "eval:loss": 0.08291440457105637, "eval:acc": 0.9639639854431152, "eval:f1 micro": 0.96, "eval:precision micro": 0.96, "eval:recall micro": 0.95, "eval:f1 macro": 0.96, "eval:precision macro": 0.97, "eval:recall macro": 0.96, "eval:f1 weighted": 0.96, "eval:precision weighted": 0.97, "eval:recall weighted": 0.95}, "post_train": {"ts": 1682538294.618661, "eval:loss": 0.08802482485771179, "eval:acc": 0.9729729890823364, "eval:f1 micro": 0.98, "eval:precision micro": 0.98, "eval:recall micro": 0.97, "eval:f1 macro": 0.98, "eval:precision macro": 0.98, "eval:recall macro": 0.97, "eval:f1 weighted": 0.98, "eval:precision weighted": 0.98, "eval:recall weighted": 0.97}, "pre_update": {}, "post_update": {}}, {"round_no": 13, "pre_train": {"ts": 1682538309.9127207, "eval:loss": 0.0794641375541687, "eval:acc": 0.9639639854431152, "eval:f1 micro": 0.96, "eval:precision micro": 0.96, "eval:recall micro": 0.96, "eval:f1 macro": 0.97, "eval:precision macro": 0.97, "eval:recall macro": 0.97, "eval:f1 weighted": 0.96, "eval:precision weighted": 0.97, "eval:recall weighted": 0.96}, "post_train": {"ts": 1682538337.3715334, "eval:loss": 0.11050757765769958, "eval:acc": 0.9639639854431152, "eval:f1 micro": 0.96, "eval:precision micro": 0.96, "eval:recall micro": 0.95, "eval:f1 macro": 0.95, "eval:precision macro": 0.97, "eval:recall macro": 0.95, "eval:f1 weighted": 0.96, "eval:precision weighted": 0.97, "eval:recall weighted": 0.95}, "pre_update": {}, "post_update": {}}, {"round_no": 14, "pre_train": {"ts": 1682538349.6168935, "eval:loss": 0.07658223062753677, "eval:acc": 0.9639639854431152, "eval:f1 micro": 0.96, "eval:precision micro": 0.96, "eval:recall micro": 0.96, "eval:f1 macro": 0.97, "eval:precision macro": 0.97, "eval:recall macro": 0.97, "eval:f1 weighted": 0.96, "eval:precision weighted": 0.97, "eval:recall weighted": 0.96}, "post_train": {"ts": 1682538377.4962885, "eval:loss": 0.09701722115278244, "eval:acc": 0.9729729890823364, "eval:f1 micro": 0.98, "eval:precision micro": 0.98, "eval:recall micro": 0.97, "eval:f1 macro": 0.98, "eval:precision macro": 0.98, "eval:recall macro": 0.97, "eval:f1 weighted": 0.98, "eval:precision weighted": 0.98, "eval:recall weighted": 0.97}, "pre_update": {}, "post_update": {}}, {"round_no": 15, "pre_train": {"ts": 1682538388.3323796, "eval:loss": 0.07444170117378235, "eval:acc": 0.9729729890823364, "eval:f1 micro": 0.97, "eval:precision micro": 0.97, "eval:recall micro": 0.97, "eval:f1 macro": 0.97, "eval:precision macro": 0.98, "eval:recall macro": 0.97, "eval:f1 weighted": 0.97, "eval:precision weighted": 0.97, "eval:recall weighted": 0.97}, "post_train": {"ts": 1682538415.9363458, "eval:loss": 0.0895356759428978, "eval:acc": 0.9729729890823364, "eval:f1 micro": 0.98, "eval:precision micro": 0.98, "eval:recall micro": 0.97, "eval:f1 macro": 0.98, "eval:precision macro": 0.98, "eval:recall macro": 0.97, "eval:f1 weighted": 0.98, "eval:precision weighted": 0.98, "eval:recall weighted": 0.97}, "pre_update": {}, "post_update": {}}, {"round_no": 16, "pre_train": {"ts": 1682538438.053324, "eval:loss": 0.0709817185997963, "eval:acc": 0.9729729890823364, "eval:f1 micro": 0.97, "eval:precision micro": 0.97, "eval:recall micro": 0.97, "eval:f1 macro": 0.97, "eval:precision macro": 0.98, "eval:recall macro": 0.97, "eval:f1 weighted": 0.97, "eval:precision weighted": 0.97, "eval:recall weighted": 0.97}, "post_train": {"ts": 1682538463.598137, "eval:loss": 0.08006636053323746, "eval:acc": 0.9729729890823364, "eval:f1 micro": 0.97, "eval:precision micro": 0.97, "eval:recall micro": 0.97, "eval:f1 macro": 0.97, "eval:precision macro": 0.98, "eval:recall macro": 0.97, "eval:f1 weighted": 0.97, "eval:precision weighted": 0.97, "eval:recall weighted": 0.97}, "pre_update": {}, "post_update": {}}, {"round_no": 17, "pre_train": {"ts": 1682538484.419498, "eval:loss": 0.07002574950456619, "eval:acc": 0.9729729890823364, "eval:f1 micro": 0.97, "eval:precision micro": 0.97, "eval:recall micro": 0.97, "eval:f1 macro": 0.97, "eval:precision macro": 0.98, "eval:recall macro": 0.97, "eval:f1 weighted": 0.97, "eval:precision weighted": 0.97, "eval:recall weighted": 0.97}, "post_train": {"ts": 1682538509.9460835, "eval:loss": 0.09794005006551743, "eval:acc": 0.9639639854431152, "eval:f1 micro": 0.97, "eval:precision micro": 0.97, "eval:recall micro": 0.96, "eval:f1 macro": 0.97, "eval:precision macro": 0.98, "eval:recall macro": 0.96, "eval:f1 weighted": 0.97, "eval:precision weighted": 0.97, "eval:recall weighted": 0.96}, "pre_update": {}, "post_update": {}}, {"round_no": 18, "pre_train": {"ts": 1682538526.693338, "eval:loss": 0.06913770735263824, "eval:acc": 0.9729729890823364, "eval:f1 micro": 0.97, "eval:precision micro": 0.97, "eval:recall micro": 0.97, "eval:f1 macro": 0.97, "eval:precision macro": 0.98, "eval:recall macro": 0.97, "eval:f1 weighted": 0.97, "eval:precision weighted": 0.97, "eval:recall weighted": 0.97}, "post_train": {"ts": 1682538553.0236032, "eval:loss": 0.10535991936922073, "eval:acc": 0.954954981803894, "eval:f1 micro": 0.95, "eval:precision micro": 0.95, "eval:recall micro": 0.95, "eval:f1 macro": 0.95, "eval:precision macro": 0.96, "eval:recall macro": 0.95, "eval:f1 weighted": 0.95, "eval:precision weighted": 0.96, "eval:recall weighted": 0.95}, "pre_update": {}, "post_update": {}}, {"round_no": 19, "pre_train": {"ts": 1682538568.0473862, "eval:loss": 0.06786651164293289, "eval:acc": 0.9729729890823364, "eval:f1 micro": 0.97, "eval:precision micro": 0.97, "eval:recall micro": 0.97, "eval:f1 macro": 0.97, "eval:precision macro": 0.98, "eval:recall macro": 0.97, "eval:f1 weighted": 0.97, "eval:precision weighted": 0.97, "eval:recall weighted": 0.97}, "post_train": {"ts": 1682538594.8574388, "eval:loss": 0.05687202513217926, "eval:acc": 0.9819819927215576, "eval:f1 micro": 0.99, "eval:precision micro": 0.99, "eval:recall micro": 0.98, "eval:f1 macro": 0.99, "eval:precision macro": 0.99, "eval:recall macro": 0.98, "eval:f1 weighted": 0.99, "eval:precision weighted": 0.99, "eval:recall weighted": 0.98}, "pre_update": {}, "post_update": {}}]
