[{"round_no": 0, "pre_train": {"ts": 1682535418.3162282}, "post_train": {"ts": 1682535437.6808689, "eval:loss": 0.68453049659729, "eval:acc": 0.8018018007278442, "eval:f1 micro": 0.74, "eval:precision micro": 0.89, "eval:recall micro": 0.64, "eval:f1 macro": 0.56, "eval:precision macro": 0.74, "eval:recall macro": 0.52, "eval:f1 weighted": 0.7, "eval:precision weighted": 0.91, "eval:recall weighted": 0.64}, "pre_update": {}, "post_update": {}}, {"round_no": 1, "pre_train": {"ts": 1682535464.4299006, "eval:loss": 0.5519360899925232, "eval:acc": 0.837837815284729, "eval:f1 micro": 0.83, "eval:precision micro": 0.98, "eval:recall micro": 0.72, "eval:f1 macro": 0.84, "eval:precision macro": 0.99, "eval:recall macro": 0.75, "eval:f1 weighted": 0.82, "eval:precision weighted": 0.98, "eval:recall weighted": 0.72}, "post_train": {"ts": 1682535475.0062976, "eval:loss": 0.3200967609882355, "eval:acc": 0.9009009003639221, "eval:f1 micro": 0.89, "eval:precision micro": 0.92, "eval:recall micro": 0.86, "eval:f1 macro": 0.89, "eval:precision macro": 0.94, "eval:recall macro": 0.87, "eval:f1 weighted": 0.89, "eval:precision weighted": 0.93, "eval:recall weighted": 0.86}, "pre_update": {}, "post_update": {}}, {"round_no": 2, "pre_train": {"ts": 1682535502.3136666, "eval:loss": 0.26100173592567444, "eval:acc": 0.9369369149208069, "eval:f1 micro": 0.92, "eval:precision micro": 0.96, "eval:recall micro": 0.87, "eval:f1 macro": 0.93, "eval:precision macro": 0.98, "eval:recall macro": 0.89, "eval:f1 weighted": 0.91, "eval:precision weighted": 0.96, "eval:recall weighted": 0.87}, "post_train": {"ts": 1682535517.072222, "eval:loss": 0.32481586933135986, "eval:acc": 0.9189189076423645, "eval:f1 micro": 0.91, "eval:precision micro": 0.92, "eval:recall micro": 0.91, "eval:f1 macro": 0.92, "eval:precision macro": 0.95, "eval:recall macro": 0.91, "eval:f1 weighted": 0.91, "eval:precision weighted": 0.93, "eval:recall weighted": 0.91}, "pre_update": {}, "post_update": {}}, {"round_no": 3, "pre_train": {"ts": 1682535538.8010645, "eval:loss": 0.19401361048221588, "eval:acc": 0.954954981803894, "eval:f1 micro": 0.95, "eval:precision micro": 0.95, "eval:recall micro": 0.95, "eval:f1 macro": 0.93, "eval:precision macro": 0.93, "eval:recall macro": 0.96, "eval:f1 weighted": 0.96, "eval:precision weighted": 0.96, "eval:recall weighted": 0.95}, "post_train": {"ts": 1682535554.7832448, "eval:loss": 0.16045533120632172, "eval:acc": 0.9639639854431152, "eval:f1 micro": 0.96, "eval:precision micro": 0.96, "eval:recall micro": 0.95, "eval:f1 macro": 0.96, "eval:precision macro": 0.98, "eval:recall macro": 0.95, "eval:f1 weighted": 0.96, "eval:precision weighted": 0.97, "eval:recall weighted": 0.95}, "pre_update": {}, "post_update": {}}, {"round_no": 4, "pre_train": {"ts": 1682535578.5726037, "eval:loss": 0.15401233732700348, "eval:acc": 0.954954981803894, "eval:f1 micro": 0.96, "eval:precision micro": 0.96, "eval:recall micro": 0.95, "eval:f1 macro": 0.96, "eval:precision macro": 0.98, "eval:recall macro": 0.96, "eval:f1 weighted": 0.96, "eval:precision weighted": 0.97, "eval:recall weighted": 0.95}, "post_train": {"ts": 1682535593.279697, "eval:loss": 0.13901938498020172, "eval:acc": 0.9369369149208069, "eval:f1 micro": 0.94, "eval:precision micro": 0.95, "eval:recall micro": 0.94, "eval:f1 macro": 0.95, "eval:precision macro": 0.96, "eval:recall macro": 0.94, "eval:f1 weighted": 0.94, "eval:precision weighted": 0.95, "eval:recall weighted": 0.94}, "pre_update": {}, "post_update": {}}, {"round_no": 5, "pre_train": {"ts": 1682535615.7178473, "eval:loss": 0.13211014866828918, "eval:acc": 0.954954981803894, "eval:f1 micro": 0.96, "eval:precision micro": 0.96, "eval:recall micro": 0.95, "eval:f1 macro": 0.96, "eval:precision macro": 0.98, "eval:recall macro": 0.96, "eval:f1 weighted": 0.96, "eval:precision weighted": 0.97, "eval:recall weighted": 0.95}, "post_train": {"ts": 1682535630.9377596, "eval:loss": 0.12238075584173203, "eval:acc": 0.9639639854431152, "eval:f1 micro": 0.96, "eval:precision micro": 0.96, "eval:recall micro": 0.95, "eval:f1 macro": 0.97, "eval:precision macro": 0.97, "eval:recall macro": 0.96, "eval:f1 weighted": 0.96, "eval:precision weighted": 0.97, "eval:recall weighted": 0.95}, "pre_update": {}, "post_update": {}}, {"round_no": 6, "pre_train": {"ts": 1682535654.4546013, "eval:loss": 0.11798128485679626, "eval:acc": 0.9639639854431152, "eval:f1 micro": 0.96, "eval:precision micro": 0.96, "eval:recall micro": 0.95, "eval:f1 macro": 0.96, "eval:precision macro": 0.98, "eval:recall macro": 0.96, "eval:f1 weighted": 0.96, "eval:precision weighted": 0.97, "eval:recall weighted": 0.95}, "post_train": {"ts": 1682535669.5432305, "eval:loss": 0.09989414364099503, "eval:acc": 0.9639639854431152, "eval:f1 micro": 0.97, "eval:precision micro": 0.97, "eval:recall micro": 0.96, "eval:f1 macro": 0.97, "eval:precision macro": 0.98, "eval:recall macro": 0.97, "eval:f1 weighted": 0.97, "eval:precision weighted": 0.97, "eval:recall weighted": 0.96}, "pre_update": {}, "post_update": {}}, {"round_no": 7, "pre_train": {"ts": 1682535691.1902797, "eval:loss": 0.10288455337285995, "eval:acc": 0.9639639854431152, "eval:f1 micro": 0.96, "eval:precision micro": 0.96, "eval:recall micro": 0.96, "eval:f1 macro": 0.97, "eval:precision macro": 0.98, "eval:recall macro": 0.96, "eval:f1 weighted": 0.96, "eval:precision weighted": 0.97, "eval:recall weighted": 0.96}, "post_train": {"ts": 1682535706.6175566, "eval:loss": 0.115261971950531, "eval:acc": 0.9639639854431152, "eval:f1 micro": 0.97, "eval:precision micro": 0.97, "eval:recall micro": 0.96, "eval:f1 macro": 0.97, "eval:precision macro": 0.98, "eval:recall macro": 0.96, "eval:f1 weighted": 0.97, "eval:precision weighted": 0.98, "eval:recall weighted": 0.96}, "pre_update": {}, "post_update": {}}, {"round_no": 8, "pre_train": {"ts": 1682535731.181886, "eval:loss": 0.0937112420797348, "eval:acc": 0.9729729890823364, "eval:f1 micro": 0.97, "eval:precision micro": 0.97, "eval:recall micro": 0.97, "eval:f1 macro": 0.98, "eval:precision macro": 0.98, "eval:recall macro": 0.97, "eval:f1 weighted": 0.97, "eval:precision weighted": 0.98, "eval:recall weighted": 0.97}, "post_train": {"ts": 1682535745.307314, "eval:loss": 0.08354084193706512, "eval:acc": 0.954954981803894, "eval:f1 micro": 0.96, "eval:precision micro": 0.96, "eval:recall micro": 0.95, "eval:f1 macro": 0.96, "eval:precision macro": 0.97, "eval:recall macro": 0.95, "eval:f1 weighted": 0.96, "eval:precision weighted": 0.97, "eval:recall weighted": 0.95}, "pre_update": {}, "post_update": {}}, {"round_no": 9, "pre_train": {"ts": 1682535769.50341, "eval:loss": 0.08271820843219757, "eval:acc": 0.9729729890823364, "eval:f1 micro": 0.97, "eval:precision micro": 0.97, "eval:recall micro": 0.97, "eval:f1 macro": 0.98, "eval:precision macro": 0.98, "eval:recall macro": 0.97, "eval:f1 weighted": 0.97, "eval:precision weighted": 0.98, "eval:recall weighted": 0.97}, "post_train": {"ts": 1682535784.3533845, "eval:loss": 0.1009049043059349, "eval:acc": 0.9729729890823364, "eval:f1 micro": 0.97, "eval:precision micro": 0.97, "eval:recall micro": 0.97, "eval:f1 macro": 0.98, "eval:precision macro": 0.98, "eval:recall macro": 0.97, "eval:f1 weighted": 0.97, "eval:precision weighted": 0.98, "eval:recall weighted": 0.97}, "pre_update": {}, "post_update": {}}, {"round_no": 10, "pre_train": {"ts": 1682535807.048619, "eval:loss": 0.07748564332723618, "eval:acc": 0.9729729890823364, "eval:f1 micro": 0.97, "eval:precision micro": 0.97, "eval:recall micro": 0.97, "eval:f1 macro": 0.98, "eval:precision macro": 0.98, "eval:recall macro": 0.97, "eval:f1 weighted": 0.97, "eval:precision weighted": 0.98, "eval:recall weighted": 0.97}, "post_train": {"ts": 1682535820.2663455, "eval:loss": 0.05916260927915573, "eval:acc": 0.9819819927215576, "eval:f1 micro": 0.98, "eval:precision micro": 0.98, "eval:recall micro": 0.98, "eval:f1 macro": 0.99, "eval:precision macro": 0.99, "eval:recall macro": 0.98, "eval:f1 weighted": 0.98, "eval:precision weighted": 0.98, "eval:recall weighted": 0.98}, "pre_update": {}, "post_update": {}}, {"round_no": 11, "pre_train": {"ts": 1682535846.7874224, "eval:loss": 0.07354990392923355, "eval:acc": 0.9729729890823364, "eval:f1 micro": 0.97, "eval:precision micro": 0.97, "eval:recall micro": 0.97, "eval:f1 macro": 0.98, "eval:precision macro": 0.98, "eval:recall macro": 0.97, "eval:f1 weighted": 0.97, "eval:precision weighted": 0.98, "eval:recall weighted": 0.97}, "post_train": {"ts": 1682535861.5478966, "eval:loss": 0.07759276032447815, "eval:acc": 0.9819819927215576, "eval:f1 micro": 0.98, "eval:precision micro": 0.98, "eval:recall micro": 0.98, "eval:f1 macro": 0.99, "eval:precision macro": 0.99, "eval:recall macro": 0.98, "eval:f1 weighted": 0.98, "eval:precision weighted": 0.98, "eval:recall weighted": 0.98}, "pre_update": {}, "post_update": {}}, {"round_no": 12, "pre_train": {"ts": 1682535887.103771, "eval:loss": 0.06827832758426666, "eval:acc": 0.9729729890823364, "eval:f1 micro": 0.97, "eval:precision micro": 0.97, "eval:recall micro": 0.97, "eval:f1 macro": 0.98, "eval:precision macro": 0.98, "eval:recall macro": 0.97, "eval:f1 weighted": 0.97, "eval:precision weighted": 0.98, "eval:recall weighted": 0.97}, "post_train": {"ts": 1682535901.7783365, "eval:loss": 0.058627836406230927, "eval:acc": 0.9819819927215576, "eval:f1 micro": 0.98, "eval:precision micro": 0.98, "eval:recall micro": 0.98, "eval:f1 macro": 0.99, "eval:precision macro": 0.99, "eval:recall macro": 0.98, "eval:f1 weighted": 0.98, "eval:precision weighted": 0.98, "eval:recall weighted": 0.98}, "pre_update": {}, "post_update": {}}, {"round_no": 13, "pre_train": {"ts": 1682535925.8903508, "eval:loss": 0.06728275120258331, "eval:acc": 0.9729729890823364, "eval:f1 micro": 0.97, "eval:precision micro": 0.97, "eval:recall micro": 0.97, "eval:f1 macro": 0.98, "eval:precision macro": 0.98, "eval:recall macro": 0.97, "eval:f1 weighted": 0.97, "eval:precision weighted": 0.98, "eval:recall weighted": 0.97}, "post_train": {"ts": 1682535941.3792453, "eval:loss": 0.07626304775476456, "eval:acc": 0.9729729890823364, "eval:f1 micro": 0.97, "eval:precision micro": 0.97, "eval:recall micro": 0.97, "eval:f1 macro": 0.97, "eval:precision macro": 0.98, "eval:recall macro": 0.97, "eval:f1 weighted": 0.97, "eval:precision weighted": 0.97, "eval:recall weighted": 0.97}, "pre_update": {}, "post_update": {}}, {"round_no": 14, "pre_train": {"ts": 1682535964.1919298, "eval:loss": 0.06335411965847015, "eval:acc": 0.9729729890823364, "eval:f1 micro": 0.97, "eval:precision micro": 0.97, "eval:recall micro": 0.97, "eval:f1 macro": 0.98, "eval:precision macro": 0.98, "eval:recall macro": 0.97, "eval:f1 weighted": 0.97, "eval:precision weighted": 0.98, "eval:recall weighted": 0.97}, "post_train": {"ts": 1682535978.0032587, "eval:loss": 0.0486036092042923, "eval:acc": 0.9819819927215576, "eval:f1 micro": 0.98, "eval:precision micro": 0.98, "eval:recall micro": 0.98, "eval:f1 macro": 0.99, "eval:precision macro": 0.99, "eval:recall macro": 0.98, "eval:f1 weighted": 0.98, "eval:precision weighted": 0.98, "eval:recall weighted": 0.98}, "pre_update": {}, "post_update": {}}, {"round_no": 15, "pre_train": {"ts": 1682536001.4119728, "eval:loss": 0.05588756129145622, "eval:acc": 0.9729729890823364, "eval:f1 micro": 0.97, "eval:precision micro": 0.97, "eval:recall micro": 0.97, "eval:f1 macro": 0.98, "eval:precision macro": 0.98, "eval:recall macro": 0.97, "eval:f1 weighted": 0.97, "eval:precision weighted": 0.98, "eval:recall weighted": 0.97}, "post_train": {"ts": 1682536017.1503248, "eval:loss": 0.04092002660036087, "eval:acc": 0.9909909963607788, "eval:f1 micro": 0.99, "eval:precision micro": 0.99, "eval:recall micro": 0.99, "eval:f1 macro": 0.99, "eval:precision macro": 0.99, "eval:recall macro": 0.99, "eval:f1 weighted": 0.99, "eval:precision weighted": 0.99, "eval:recall weighted": 0.99}, "pre_update": {}, "post_update": {}}, {"round_no": 16, "pre_train": {"ts": 1682536040.1905236, "eval:loss": 0.05710164085030556, "eval:acc": 0.9729729890823364, "eval:f1 micro": 0.97, "eval:precision micro": 0.97, "eval:recall micro": 0.97, "eval:f1 macro": 0.98, "eval:precision macro": 0.98, "eval:recall macro": 0.97, "eval:f1 weighted": 0.97, "eval:precision weighted": 0.98, "eval:recall weighted": 0.97}, "post_train": {"ts": 1682536054.7931209, "eval:loss": 0.04497844725847244, "eval:acc": 0.9819819927215576, "eval:f1 micro": 0.98, "eval:precision micro": 0.98, "eval:recall micro": 0.98, "eval:f1 macro": 0.99, "eval:precision macro": 0.99, "eval:recall macro": 0.98, "eval:f1 weighted": 0.98, "eval:precision weighted": 0.98, "eval:recall weighted": 0.98}, "pre_update": {}, "post_update": {}}, {"round_no": 17, "pre_train": {"ts": 1682536077.7909362, "eval:loss": 0.056105248630046844, "eval:acc": 0.9729729890823364, "eval:f1 micro": 0.97, "eval:precision micro": 0.97, "eval:recall micro": 0.97, "eval:f1 macro": 0.98, "eval:precision macro": 0.98, "eval:recall macro": 0.97, "eval:f1 weighted": 0.97, "eval:precision weighted": 0.98, "eval:recall weighted": 0.97}, "post_train": {"ts": 1682536094.082827, "eval:loss": 0.062164973467588425, "eval:acc": 0.9819819927215576, "eval:f1 micro": 0.98, "eval:precision micro": 0.98, "eval:recall micro": 0.98, "eval:f1 macro": 0.99, "eval:precision macro": 0.99, "eval:recall macro": 0.98, "eval:f1 weighted": 0.98, "eval:precision weighted": 0.98, "eval:recall weighted": 0.98}, "pre_update": {}, "post_update": {}}, {"round_no": 18, "pre_train": {"ts": 1682536118.2224991, "eval:loss": 0.05326378718018532, "eval:acc": 0.9729729890823364, "eval:f1 micro": 0.97, "eval:precision micro": 0.97, "eval:recall micro": 0.97, "eval:f1 macro": 0.98, "eval:precision macro": 0.98, "eval:recall macro": 0.97, "eval:f1 weighted": 0.97, "eval:precision weighted": 0.98, "eval:recall weighted": 0.97}, "post_train": {"ts": 1682536132.6156082, "eval:loss": 0.056922271847724915, "eval:acc": 0.9819819927215576, "eval:f1 micro": 0.98, "eval:precision micro": 0.98, "eval:recall micro": 0.98, "eval:f1 macro": 0.99, "eval:precision macro": 0.99, "eval:recall macro": 0.98, "eval:f1 weighted": 0.98, "eval:precision weighted": 0.98, "eval:recall weighted": 0.98}, "pre_update": {}, "post_update": {}}, {"round_no": 19, "pre_train": {"ts": 1682536157.3887792, "eval:loss": 0.050400931388139725, "eval:acc": 0.9729729890823364, "eval:f1 micro": 0.97, "eval:precision micro": 0.97, "eval:recall micro": 0.97, "eval:f1 macro": 0.98, "eval:precision macro": 0.98, "eval:recall macro": 0.97, "eval:f1 weighted": 0.97, "eval:precision weighted": 0.98, "eval:recall weighted": 0.97}, "post_train": {"ts": 1682536173.2890348, "eval:loss": 0.06463716179132462, "eval:acc": 0.9819819927215576, "eval:f1 micro": 0.98, "eval:precision micro": 0.98, "eval:recall micro": 0.98, "eval:f1 macro": 0.99, "eval:precision macro": 0.99, "eval:recall macro": 0.98, "eval:f1 weighted": 0.98, "eval:precision weighted": 0.98, "eval:recall weighted": 0.98}, "pre_update": {}, "post_update": {}}]
