[{"round_no": 0, "pre_train": {"ts": 1682541021.8174965}, "post_train": {"ts": 1682541058.4314466, "eval:loss": 0.8072803020477295, "eval:acc": 0.7477477192878723, "eval:f1 micro": 0.71, "eval:precision micro": 0.9, "eval:recall micro": 0.59, "eval:f1 macro": 0.67, "eval:precision macro": 0.83, "eval:recall macro": 0.6, "eval:f1 weighted": 0.65, "eval:precision weighted": 0.81, "eval:recall weighted": 0.59}, "pre_update": {}, "post_update": {}}, {"round_no": 1, "pre_train": {"ts": 1682541108.0574267, "eval:loss": 0.5483659505844116, "eval:acc": 0.8648648858070374, "eval:f1 micro": 0.85, "eval:precision micro": 0.98, "eval:recall micro": 0.75, "eval:f1 macro": 0.81, "eval:precision macro": 0.98, "eval:recall macro": 0.72, "eval:f1 weighted": 0.83, "eval:precision weighted": 0.98, "eval:recall weighted": 0.75}, "post_train": {"ts": 1682541135.0834663, "eval:loss": 0.5247734785079956, "eval:acc": 0.837837815284729, "eval:f1 micro": 0.84, "eval:precision micro": 0.86, "eval:recall micro": 0.82, "eval:f1 macro": 0.83, "eval:precision macro": 0.88, "eval:recall macro": 0.85, "eval:f1 weighted": 0.83, "eval:precision weighted": 0.9, "eval:recall weighted": 0.82}, "pre_update": {}, "post_update": {}}, {"round_no": 2, "pre_train": {"ts": 1682541183.7801015, "eval:loss": 0.2874862253665924, "eval:acc": 0.9369369149208069, "eval:f1 micro": 0.93, "eval:precision micro": 0.96, "eval:recall micro": 0.89, "eval:f1 macro": 0.9, "eval:precision macro": 0.95, "eval:recall macro": 0.88, "eval:f1 weighted": 0.92, "eval:precision weighted": 0.96, "eval:recall weighted": 0.89}, "post_train": {"ts": 1682541206.4908755, "eval:loss": 0.34398260712623596, "eval:acc": 0.9099099040031433, "eval:f1 micro": 0.92, "eval:precision micro": 0.93, "eval:recall micro": 0.91, "eval:f1 macro": 0.92, "eval:precision macro": 0.92, "eval:recall macro": 0.93, "eval:f1 weighted": 0.92, "eval:precision weighted": 0.94, "eval:recall weighted": 0.91}, "pre_update": {}, "post_update": {}}, {"round_no": 3, "pre_train": {"ts": 1682541246.1749191, "eval:loss": 0.23641781508922577, "eval:acc": 0.9459459185600281, "eval:f1 micro": 0.94, "eval:precision micro": 0.95, "eval:recall micro": 0.93, "eval:f1 macro": 0.93, "eval:precision macro": 0.94, "eval:recall macro": 0.92, "eval:f1 weighted": 0.94, "eval:precision weighted": 0.95, "eval:recall weighted": 0.93}, "post_train": {"ts": 1682541249.6755073, "eval:loss": 0.2945108115673065, "eval:acc": 0.954954981803894, "eval:f1 micro": 0.94, "eval:precision micro": 0.96, "eval:recall micro": 0.93, "eval:f1 macro": 0.94, "eval:precision macro": 0.96, "eval:recall macro": 0.93, "eval:f1 weighted": 0.94, "eval:precision weighted": 0.97, "eval:recall weighted": 0.93}, "pre_update": {}, "post_update": {}}, {"round_no": 4, "pre_train": {"ts": 1682541309.8689482, "eval:loss": 0.20503368973731995, "eval:acc": 0.9639639854431152, "eval:f1 micro": 0.95, "eval:precision micro": 0.97, "eval:recall micro": 0.94, "eval:f1 macro": 0.94, "eval:precision macro": 0.96, "eval:recall macro": 0.92, "eval:f1 weighted": 0.95, "eval:precision weighted": 0.97, "eval:recall weighted": 0.94}, "post_train": {"ts": 1682541328.2253628, "eval:loss": 0.24125820398330688, "eval:acc": 0.954954981803894, "eval:f1 micro": 0.95, "eval:precision micro": 0.95, "eval:recall micro": 0.95, "eval:f1 macro": 0.95, "eval:precision macro": 0.96, "eval:recall macro": 0.95, "eval:f1 weighted": 0.95, "eval:precision weighted": 0.96, "eval:recall weighted": 0.95}, "pre_update": {}, "post_update": {}}, {"round_no": 5, "pre_train": {"ts": 1682541374.7332332, "eval:loss": 0.18652848899364471, "eval:acc": 0.9639639854431152, "eval:f1 micro": 0.96, "eval:precision micro": 0.97, "eval:recall micro": 0.95, "eval:f1 macro": 0.95, "eval:precision macro": 0.96, "eval:recall macro": 0.93, "eval:f1 weighted": 0.96, "eval:precision weighted": 0.97, "eval:recall weighted": 0.95}, "post_train": {"ts": 1682541385.3011725, "eval:loss": 0.24460041522979736, "eval:acc": 0.9639639854431152, "eval:f1 micro": 0.95, "eval:precision micro": 0.96, "eval:recall micro": 0.94, "eval:f1 macro": 0.95, "eval:precision macro": 0.97, "eval:recall macro": 0.93, "eval:f1 weighted": 0.95, "eval:precision weighted": 0.97, "eval:recall weighted": 0.94}, "pre_update": {}, "post_update": {}}, {"round_no": 6, "pre_train": {"ts": 1682541449.1022038, "eval:loss": 0.17080047726631165, "eval:acc": 0.9639639854431152, "eval:f1 micro": 0.96, "eval:precision micro": 0.97, "eval:recall micro": 0.95, "eval:f1 macro": 0.95, "eval:precision macro": 0.96, "eval:recall macro": 0.93, "eval:f1 weighted": 0.96, "eval:precision weighted": 0.97, "eval:recall weighted": 0.95}, "post_train": {"ts": 1682541472.5062122, "eval:loss": 0.18849553167819977, "eval:acc": 0.9819819927215576, "eval:f1 micro": 0.98, "eval:precision micro": 0.98, "eval:recall micro": 0.98, "eval:f1 macro": 0.98, "eval:precision macro": 0.98, "eval:recall macro": 0.98, "eval:f1 weighted": 0.98, "eval:precision weighted": 0.98, "eval:recall weighted": 0.98}, "pre_update": {}, "post_update": {}}, {"round_no": 7, "pre_train": {"ts": 1682541510.153224, "eval:loss": 0.15919946134090424, "eval:acc": 0.9639639854431152, "eval:f1 micro": 0.96, "eval:precision micro": 0.97, "eval:recall micro": 0.95, "eval:f1 macro": 0.96, "eval:precision macro": 0.97, "eval:recall macro": 0.95, "eval:f1 weighted": 0.96, "eval:precision weighted": 0.97, "eval:recall weighted": 0.95}, "post_train": {"ts": 1682541511.1855214, "eval:loss": 0.19545826315879822, "eval:acc": 0.9729729890823364, "eval:f1 micro": 0.96, "eval:precision micro": 0.97, "eval:recall micro": 0.95, "eval:f1 macro": 0.95, "eval:precision macro": 0.97, "eval:recall macro": 0.94, "eval:f1 weighted": 0.96, "eval:precision weighted": 0.97, "eval:recall weighted": 0.95}, "pre_update": {}, "post_update": {}}, {"round_no": 8, "pre_train": {"ts": 1682541575.9405937, "eval:loss": 0.1513831615447998, "eval:acc": 0.9639639854431152, "eval:f1 micro": 0.97, "eval:precision micro": 0.97, "eval:recall micro": 0.96, "eval:f1 macro": 0.96, "eval:precision macro": 0.97, "eval:recall macro": 0.96, "eval:f1 weighted": 0.97, "eval:precision weighted": 0.98, "eval:recall weighted": 0.96}, "post_train": {"ts": 1682541577.5609593, "eval:loss": 0.18398486077785492, "eval:acc": 0.9729729890823364, "eval:f1 micro": 0.97, "eval:precision micro": 0.97, "eval:recall micro": 0.97, "eval:f1 macro": 0.97, "eval:precision macro": 0.97, "eval:recall macro": 0.97, "eval:f1 weighted": 0.97, "eval:precision weighted": 0.98, "eval:recall weighted": 0.97}, "pre_update": {}, "post_update": {}}, {"round_no": 9, "pre_train": {"ts": 1682541636.84812, "eval:loss": 0.1440153419971466, "eval:acc": 0.9729729890823364, "eval:f1 micro": 0.97, "eval:precision micro": 0.97, "eval:recall micro": 0.97, "eval:f1 macro": 0.97, "eval:precision macro": 0.97, "eval:recall macro": 0.97, "eval:f1 weighted": 0.97, "eval:precision weighted": 0.98, "eval:recall weighted": 0.97}, "post_train": {"ts": 1682541641.1137695, "eval:loss": 0.17821653187274933, "eval:acc": 0.9729729890823364, "eval:f1 micro": 0.98, "eval:precision micro": 0.98, "eval:recall micro": 0.97, "eval:f1 macro": 0.97, "eval:precision macro": 0.98, "eval:recall macro": 0.97, "eval:f1 weighted": 0.98, "eval:precision weighted": 0.98, "eval:recall weighted": 0.97}, "pre_update": {}, "post_update": {}}, {"round_no": 10, "pre_train": {"ts": 1682541706.63031, "eval:loss": 0.1396183967590332, "eval:acc": 0.9729729890823364, "eval:f1 micro": 0.97, "eval:precision micro": 0.97, "eval:recall micro": 0.97, "eval:f1 macro": 0.97, "eval:precision macro": 0.97, "eval:recall macro": 0.97, "eval:f1 weighted": 0.97, "eval:precision weighted": 0.98, "eval:recall weighted": 0.97}, "post_train": {"ts": 1682541722.842941, "eval:loss": 0.1707257777452469, "eval:acc": 0.9729729890823364, "eval:f1 micro": 0.98, "eval:precision micro": 0.98, "eval:recall micro": 0.97, "eval:f1 macro": 0.98, "eval:precision macro": 0.98, "eval:recall macro": 0.98, "eval:f1 weighted": 0.98, "eval:precision weighted": 0.98, "eval:recall weighted": 0.97}, "pre_update": {}, "post_update": {}}, {"round_no": 11, "pre_train": {"ts": 1682541773.2794657, "eval:loss": 0.13636839389801025, "eval:acc": 0.9819819927215576, "eval:f1 micro": 0.98, "eval:precision micro": 0.98, "eval:recall micro": 0.98, "eval:f1 macro": 0.98, "eval:precision macro": 0.98, "eval:recall macro": 0.98, "eval:f1 weighted": 0.98, "eval:precision weighted": 0.98, "eval:recall weighted": 0.98}, "post_train": {"ts": 1682541791.440146, "eval:loss": 0.18952976167201996, "eval:acc": 0.9819819927215576, "eval:f1 micro": 0.98, "eval:precision micro": 0.98, "eval:recall micro": 0.97, "eval:f1 macro": 0.97, "eval:precision macro": 0.98, "eval:recall macro": 0.97, "eval:f1 weighted": 0.98, "eval:precision weighted": 0.98, "eval:recall weighted": 0.97}, "pre_update": {}, "post_update": {}}, {"round_no": 12, "pre_train": {"ts": 1682541836.7911777, "eval:loss": 0.13665372133255005, "eval:acc": 0.9819819927215576, "eval:f1 micro": 0.98, "eval:precision micro": 0.98, "eval:recall micro": 0.98, "eval:f1 macro": 0.98, "eval:precision macro": 0.98, "eval:recall macro": 0.98, "eval:f1 weighted": 0.98, "eval:precision weighted": 0.98, "eval:recall weighted": 0.98}, "post_train": {"ts": 1682541851.9790852, "eval:loss": 0.15886470675468445, "eval:acc": 0.9729729890823364, "eval:f1 micro": 0.97, "eval:precision micro": 0.97, "eval:recall micro": 0.97, "eval:f1 macro": 0.97, "eval:precision macro": 0.97, "eval:recall macro": 0.97, "eval:f1 weighted": 0.97, "eval:precision weighted": 0.98, "eval:recall weighted": 0.97}, "pre_update": {}, "post_update": {}}, {"round_no": 13, "pre_train": {"ts": 1682541903.1499643, "eval:loss": 0.1307423859834671, "eval:acc": 0.9819819927215576, "eval:f1 micro": 0.98, "eval:precision micro": 0.98, "eval:recall micro": 0.98, "eval:f1 macro": 0.98, "eval:precision macro": 0.98, "eval:recall macro": 0.98, "eval:f1 weighted": 0.98, "eval:precision weighted": 0.98, "eval:recall weighted": 0.98}, "post_train": {"ts": 1682541904.1689873, "eval:loss": 0.15005344152450562, "eval:acc": 0.9729729890823364, "eval:f1 micro": 0.98, "eval:precision micro": 0.98, "eval:recall micro": 0.97, "eval:f1 macro": 0.97, "eval:precision macro": 0.98, "eval:recall macro": 0.97, "eval:f1 weighted": 0.98, "eval:precision weighted": 0.98, "eval:recall weighted": 0.97}, "pre_update": {}, "post_update": {}}, {"round_no": 14, "pre_train": {"ts": 1682541980.311233, "eval:loss": 0.12725889682769775, "eval:acc": 0.9819819927215576, "eval:f1 micro": 0.98, "eval:precision micro": 0.98, "eval:recall micro": 0.98, "eval:f1 macro": 0.98, "eval:precision macro": 0.98, "eval:recall macro": 0.98, "eval:f1 weighted": 0.98, "eval:precision weighted": 0.98, "eval:recall weighted": 0.98}, "post_train": {"ts": 1682542001.0637684, "eval:loss": 0.16379769146442413, "eval:acc": 0.9729729890823364, "eval:f1 micro": 0.98, "eval:precision micro": 0.98, "eval:recall micro": 0.97, "eval:f1 macro": 0.97, "eval:precision macro": 0.98, "eval:recall macro": 0.97, "eval:f1 weighted": 0.98, "eval:precision weighted": 0.98, "eval:recall weighted": 0.97}, "pre_update": {}, "post_update": {}}, {"round_no": 15, "pre_train": {"ts": 1682542040.1366093, "eval:loss": 0.12524697184562683, "eval:acc": 0.9819819927215576, "eval:f1 micro": 0.98, "eval:precision micro": 0.98, "eval:recall micro": 0.98, "eval:f1 macro": 0.98, "eval:precision macro": 0.98, "eval:recall macro": 0.98, "eval:f1 weighted": 0.98, "eval:precision weighted": 0.98, "eval:recall weighted": 0.98}, "post_train": {"ts": 1682542055.1123757, "eval:loss": 0.14734289050102234, "eval:acc": 0.9729729890823364, "eval:f1 micro": 0.98, "eval:precision micro": 0.98, "eval:recall micro": 0.97, "eval:f1 macro": 0.97, "eval:precision macro": 0.98, "eval:recall macro": 0.97, "eval:f1 weighted": 0.98, "eval:precision weighted": 0.98, "eval:recall weighted": 0.97}, "pre_update": {}, "post_update": {}}, {"round_no": 16, "pre_train": {"ts": 1682542105.2786753, "eval:loss": 0.12403470277786255, "eval:acc": 0.9819819927215576, "eval:f1 micro": 0.98, "eval:precision micro": 0.98, "eval:recall micro": 0.98, "eval:f1 macro": 0.98, "eval:precision macro": 0.98, "eval:recall macro": 0.98, "eval:f1 weighted": 0.98, "eval:precision weighted": 0.98, "eval:recall weighted": 0.98}, "post_train": {"ts": 1682542106.433164, "eval:loss": 0.1357555091381073, "eval:acc": 0.9819819927215576, "eval:f1 micro": 0.98, "eval:precision micro": 0.98, "eval:recall micro": 0.97, "eval:f1 macro": 0.97, "eval:precision macro": 0.98, "eval:recall macro": 0.97, "eval:f1 weighted": 0.98, "eval:precision weighted": 0.98, "eval:recall weighted": 0.97}, "pre_update": {}, "post_update": {}}, {"round_no": 17, "pre_train": {"ts": 1682542169.9567995, "eval:loss": 0.12236898392438889, "eval:acc": 0.9819819927215576, "eval:f1 micro": 0.98, "eval:precision micro": 0.98, "eval:recall micro": 0.98, "eval:f1 macro": 0.98, "eval:precision macro": 0.98, "eval:recall macro": 0.98, "eval:f1 weighted": 0.98, "eval:precision weighted": 0.98, "eval:recall weighted": 0.98}, "post_train": {"ts": 1682542171.6269128, "eval:loss": 0.14166665077209473, "eval:acc": 0.9729729890823364, "eval:f1 micro": 0.97, "eval:precision micro": 0.97, "eval:recall micro": 0.97, "eval:f1 macro": 0.97, "eval:precision macro": 0.97, "eval:recall macro": 0.97, "eval:f1 weighted": 0.97, "eval:precision weighted": 0.98, "eval:recall weighted": 0.97}, "pre_update": {}, "post_update": {}}, {"round_no": 18, "pre_train": {"ts": 1682542238.8952634, "eval:loss": 0.12445162236690521, "eval:acc": 0.9819819927215576, "eval:f1 micro": 0.98, "eval:precision micro": 0.98, "eval:recall micro": 0.98, "eval:f1 macro": 0.98, "eval:precision macro": 0.98, "eval:recall macro": 0.98, "eval:f1 weighted": 0.98, "eval:precision weighted": 0.98, "eval:recall weighted": 0.98}, "post_train": {"ts": 1682542253.9964652, "eval:loss": 0.14292320609092712, "eval:acc": 0.9819819927215576, "eval:f1 micro": 0.98, "eval:precision micro": 0.98, "eval:recall micro": 0.98, "eval:f1 macro": 0.98, "eval:precision macro": 0.98, "eval:recall macro": 0.98, "eval:f1 weighted": 0.98, "eval:precision weighted": 0.98, "eval:recall weighted": 0.98}, "pre_update": {}, "post_update": {}}, {"round_no": 19, "pre_train": {"ts": 1682542303.0481482, "eval:loss": 0.12374863028526306, "eval:acc": 0.9819819927215576, "eval:f1 micro": 0.98, "eval:precision micro": 0.98, "eval:recall micro": 0.98, "eval:f1 macro": 0.98, "eval:precision macro": 0.98, "eval:recall macro": 0.98, "eval:f1 weighted": 0.98, "eval:precision weighted": 0.98, "eval:recall weighted": 0.98}, "post_train": {"ts": 1682542324.186992, "eval:loss": 0.14313244819641113, "eval:acc": 0.9729729890823364, "eval:f1 micro": 0.97, "eval:precision micro": 0.97, "eval:recall micro": 0.97, "eval:f1 macro": 0.97, "eval:precision macro": 0.97, "eval:recall macro": 0.97, "eval:f1 weighted": 0.97, "eval:precision weighted": 0.98, "eval:recall weighted": 0.97}, "pre_update": {}, "post_update": {}}]
