[{"round_no": 0, "pre_train": {"ts": 1682523665.3530726}, "post_train": {"ts": 1682523694.2718685, "eval:loss": 0.7834868431091309, "eval:acc": 0.7207207083702087, "eval:f1 micro": 0.75, "eval:precision micro": 0.84, "eval:recall micro": 0.68, "eval:f1 macro": 0.71, "eval:precision macro": 0.81, "eval:recall macro": 0.68, "eval:f1 weighted": 0.74, "eval:precision weighted": 0.88, "eval:recall weighted": 0.68}, "pre_update": {}, "post_update": {}}, {"round_no": 1, "pre_train": {"ts": 1682523710.8624938, "eval:loss": 0.5458239912986755, "eval:acc": 0.8738738894462585, "eval:f1 micro": 0.85, "eval:precision micro": 0.97, "eval:recall micro": 0.76, "eval:f1 macro": 0.81, "eval:precision macro": 0.98, "eval:recall macro": 0.71, "eval:f1 weighted": 0.83, "eval:precision weighted": 0.97, "eval:recall weighted": 0.76}, "post_train": {"ts": 1682523739.9549174, "eval:loss": 0.592893660068512, "eval:acc": 0.8108108043670654, "eval:f1 micro": 0.81, "eval:precision micro": 0.84, "eval:recall micro": 0.78, "eval:f1 macro": 0.77, "eval:precision macro": 0.84, "eval:recall macro": 0.75, "eval:f1 weighted": 0.8, "eval:precision weighted": 0.87, "eval:recall weighted": 0.78}, "pre_update": {}, "post_update": {}}, {"round_no": 2, "pre_train": {"ts": 1682523749.2749841, "eval:loss": 0.28281286358833313, "eval:acc": 0.954954981803894, "eval:f1 micro": 0.94, "eval:precision micro": 0.97, "eval:recall micro": 0.91, "eval:f1 macro": 0.93, "eval:precision macro": 0.96, "eval:recall macro": 0.91, "eval:f1 weighted": 0.94, "eval:precision weighted": 0.98, "eval:recall weighted": 0.91}, "post_train": {"ts": 1682523779.1945078, "eval:loss": 0.3581320345401764, "eval:acc": 0.9189189076423645, "eval:f1 micro": 0.93, "eval:precision micro": 0.94, "eval:recall micro": 0.91, "eval:f1 macro": 0.91, "eval:precision macro": 0.94, "eval:recall macro": 0.88, "eval:f1 weighted": 0.93, "eval:precision weighted": 0.95, "eval:recall weighted": 0.91}, "pre_update": {}, "post_update": {}}, {"round_no": 3, "pre_train": {"ts": 1682523793.2388282, "eval:loss": 0.22559858858585358, "eval:acc": 0.9639639854431152, "eval:f1 micro": 0.96, "eval:precision micro": 0.97, "eval:recall micro": 0.95, "eval:f1 macro": 0.96, "eval:precision macro": 0.96, "eval:recall macro": 0.96, "eval:f1 weighted": 0.96, "eval:precision weighted": 0.98, "eval:recall weighted": 0.95}, "post_train": {"ts": 1682523819.659129, "eval:loss": 0.26065361499786377, "eval:acc": 0.954954981803894, "eval:f1 micro": 0.95, "eval:precision micro": 0.96, "eval:recall micro": 0.95, "eval:f1 macro": 0.95, "eval:precision macro": 0.96, "eval:recall macro": 0.95, "eval:f1 weighted": 0.95, "eval:precision weighted": 0.97, "eval:recall weighted": 0.95}, "pre_update": {}, "post_update": {}}, {"round_no": 4, "pre_train": {"ts": 1682523833.461541, "eval:loss": 0.19556699693202972, "eval:acc": 0.9639639854431152, "eval:f1 micro": 0.97, "eval:precision micro": 0.97, "eval:recall micro": 0.96, "eval:f1 macro": 0.97, "eval:precision macro": 0.96, "eval:recall macro": 0.97, "eval:f1 weighted": 0.97, "eval:precision weighted": 0.98, "eval:recall weighted": 0.96}, "post_train": {"ts": 1682523859.4320757, "eval:loss": 0.26236313581466675, "eval:acc": 0.9369369149208069, "eval:f1 micro": 0.94, "eval:precision micro": 0.95, "eval:recall micro": 0.93, "eval:f1 macro": 0.93, "eval:precision macro": 0.94, "eval:recall macro": 0.93, "eval:f1 weighted": 0.94, "eval:precision weighted": 0.96, "eval:recall weighted": 0.93}, "pre_update": {}, "post_update": {}}, {"round_no": 5, "pre_train": {"ts": 1682523872.318352, "eval:loss": 0.18016453087329865, "eval:acc": 0.9729729890823364, "eval:f1 micro": 0.97, "eval:precision micro": 0.97, "eval:recall micro": 0.96, "eval:f1 macro": 0.97, "eval:precision macro": 0.96, "eval:recall macro": 0.97, "eval:f1 weighted": 0.97, "eval:precision weighted": 0.98, "eval:recall weighted": 0.96}, "post_train": {"ts": 1682523899.408885, "eval:loss": 0.22185258567333221, "eval:acc": 0.954954981803894, "eval:f1 micro": 0.95, "eval:precision micro": 0.95, "eval:recall micro": 0.95, "eval:f1 macro": 0.94, "eval:precision macro": 0.94, "eval:recall macro": 0.95, "eval:f1 weighted": 0.95, "eval:precision weighted": 0.96, "eval:recall weighted": 0.95}, "pre_update": {}, "post_update": {}}, {"round_no": 6, "pre_train": {"ts": 1682523910.4566555, "eval:loss": 0.16828465461730957, "eval:acc": 0.9729729890823364, "eval:f1 micro": 0.97, "eval:precision micro": 0.97, "eval:recall micro": 0.96, "eval:f1 macro": 0.97, "eval:precision macro": 0.96, "eval:recall macro": 0.97, "eval:f1 weighted": 0.97, "eval:precision weighted": 0.98, "eval:recall weighted": 0.96}, "post_train": {"ts": 1682523937.5091577, "eval:loss": 0.2083543837070465, "eval:acc": 0.9369369149208069, "eval:f1 micro": 0.95, "eval:precision micro": 0.95, "eval:recall micro": 0.94, "eval:f1 macro": 0.93, "eval:precision macro": 0.95, "eval:recall macro": 0.93, "eval:f1 weighted": 0.94, "eval:precision weighted": 0.96, "eval:recall weighted": 0.94}, "pre_update": {}, "post_update": {}}, {"round_no": 7, "pre_train": {"ts": 1682523953.443708, "eval:loss": 0.15509270131587982, "eval:acc": 0.9819819927215576, "eval:f1 micro": 0.98, "eval:precision micro": 0.98, "eval:recall micro": 0.98, "eval:f1 macro": 0.98, "eval:precision macro": 0.97, "eval:recall macro": 0.99, "eval:f1 weighted": 0.98, "eval:precision weighted": 0.98, "eval:recall weighted": 0.98}, "post_train": {"ts": 1682523980.2388387, "eval:loss": 0.18542291224002838, "eval:acc": 0.9729729890823364, "eval:f1 micro": 0.98, "eval:precision micro": 0.98, "eval:recall micro": 0.97, "eval:f1 macro": 0.97, "eval:precision macro": 0.97, "eval:recall macro": 0.97, "eval:f1 weighted": 0.98, "eval:precision weighted": 0.98, "eval:recall weighted": 0.97}, "pre_update": {}, "post_update": {}}, {"round_no": 8, "pre_train": {"ts": 1682523987.12767, "eval:loss": 0.14892683923244476, "eval:acc": 0.9819819927215576, "eval:f1 micro": 0.98, "eval:precision micro": 0.98, "eval:recall micro": 0.98, "eval:f1 macro": 0.98, "eval:precision macro": 0.97, "eval:recall macro": 0.99, "eval:f1 weighted": 0.98, "eval:precision weighted": 0.98, "eval:recall weighted": 0.98}, "post_train": {"ts": 1682524016.9565816, "eval:loss": 0.15928897261619568, "eval:acc": 0.9729729890823364, "eval:f1 micro": 0.97, "eval:precision micro": 0.97, "eval:recall micro": 0.97, "eval:f1 macro": 0.96, "eval:precision macro": 0.96, "eval:recall macro": 0.97, "eval:f1 weighted": 0.97, "eval:precision weighted": 0.98, "eval:recall weighted": 0.97}, "pre_update": {}, "post_update": {}}, {"round_no": 9, "pre_train": {"ts": 1682524027.7687895, "eval:loss": 0.14224688708782196, "eval:acc": 0.9819819927215576, "eval:f1 micro": 0.98, "eval:precision micro": 0.98, "eval:recall micro": 0.98, "eval:f1 macro": 0.98, "eval:precision macro": 0.97, "eval:recall macro": 0.99, "eval:f1 weighted": 0.98, "eval:precision weighted": 0.98, "eval:recall weighted": 0.98}, "post_train": {"ts": 1682524056.5751271, "eval:loss": 0.18405933678150177, "eval:acc": 0.9639639854431152, "eval:f1 micro": 0.96, "eval:precision micro": 0.96, "eval:recall micro": 0.96, "eval:f1 macro": 0.96, "eval:precision macro": 0.96, "eval:recall macro": 0.97, "eval:f1 weighted": 0.96, "eval:precision weighted": 0.97, "eval:recall weighted": 0.96}, "pre_update": {}, "post_update": {}}, {"round_no": 10, "pre_train": {"ts": 1682524071.5589306, "eval:loss": 0.13417379558086395, "eval:acc": 0.9819819927215576, "eval:f1 micro": 0.98, "eval:precision micro": 0.98, "eval:recall micro": 0.98, "eval:f1 macro": 0.98, "eval:precision macro": 0.97, "eval:recall macro": 0.99, "eval:f1 weighted": 0.98, "eval:precision weighted": 0.98, "eval:recall weighted": 0.98}, "post_train": {"ts": 1682524098.2820895, "eval:loss": 0.16698162257671356, "eval:acc": 0.9729729890823364, "eval:f1 micro": 0.97, "eval:precision micro": 0.97, "eval:recall micro": 0.97, "eval:f1 macro": 0.96, "eval:precision macro": 0.95, "eval:recall macro": 0.97, "eval:f1 weighted": 0.97, "eval:precision weighted": 0.98, "eval:recall weighted": 0.97}, "pre_update": {}, "post_update": {}}, {"round_no": 11, "pre_train": {"ts": 1682524116.8174372, "eval:loss": 0.1317790448665619, "eval:acc": 0.9729729890823364, "eval:f1 micro": 0.97, "eval:precision micro": 0.97, "eval:recall micro": 0.97, "eval:f1 macro": 0.97, "eval:precision macro": 0.96, "eval:recall macro": 0.98, "eval:f1 weighted": 0.97, "eval:precision weighted": 0.98, "eval:recall weighted": 0.97}, "post_train": {"ts": 1682524142.2154424, "eval:loss": 0.1451859325170517, "eval:acc": 0.9819819927215576, "eval:f1 micro": 0.98, "eval:precision micro": 0.98, "eval:recall micro": 0.98, "eval:f1 macro": 0.98, "eval:precision macro": 0.97, "eval:recall macro": 0.99, "eval:f1 weighted": 0.98, "eval:precision weighted": 0.98, "eval:recall weighted": 0.98}, "pre_update": {}, "post_update": {}}, {"round_no": 12, "pre_train": {"ts": 1682524155.2751782, "eval:loss": 0.12498043477535248, "eval:acc": 0.9819819927215576, "eval:f1 micro": 0.98, "eval:precision micro": 0.98, "eval:recall micro": 0.97, "eval:f1 macro": 0.97, "eval:precision macro": 0.97, "eval:recall macro": 0.98, "eval:f1 weighted": 0.98, "eval:precision weighted": 0.98, "eval:recall weighted": 0.97}, "post_train": {"ts": 1682524182.1218872, "eval:loss": 0.14490455389022827, "eval:acc": 0.9639639854431152, "eval:f1 micro": 0.96, "eval:precision micro": 0.96, "eval:recall micro": 0.96, "eval:f1 macro": 0.95, "eval:precision macro": 0.94, "eval:recall macro": 0.97, "eval:f1 weighted": 0.97, "eval:precision weighted": 0.97, "eval:recall weighted": 0.96}, "pre_update": {}, "post_update": {}}, {"round_no": 13, "pre_train": {"ts": 1682524194.899612, "eval:loss": 0.12039869278669357, "eval:acc": 0.9729729890823364, "eval:f1 micro": 0.97, "eval:precision micro": 0.97, "eval:recall micro": 0.97, "eval:f1 macro": 0.97, "eval:precision macro": 0.96, "eval:recall macro": 0.98, "eval:f1 weighted": 0.97, "eval:precision weighted": 0.98, "eval:recall weighted": 0.97}, "post_train": {"ts": 1682524222.4970958, "eval:loss": 0.14132589101791382, "eval:acc": 0.9729729890823364, "eval:f1 micro": 0.97, "eval:precision micro": 0.97, "eval:recall micro": 0.97, "eval:f1 macro": 0.97, "eval:precision macro": 0.96, "eval:recall macro": 0.98, "eval:f1 weighted": 0.97, "eval:precision weighted": 0.98, "eval:recall weighted": 0.97}, "pre_update": {}, "post_update": {}}, {"round_no": 14, "pre_train": {"ts": 1682524237.7277982, "eval:loss": 0.11862166225910187, "eval:acc": 0.9729729890823364, "eval:f1 micro": 0.97, "eval:precision micro": 0.97, "eval:recall micro": 0.97, "eval:f1 macro": 0.97, "eval:precision macro": 0.96, "eval:recall macro": 0.98, "eval:f1 weighted": 0.97, "eval:precision weighted": 0.98, "eval:recall weighted": 0.97}, "post_train": {"ts": 1682524264.4828959, "eval:loss": 0.12262297421693802, "eval:acc": 0.9729729890823364, "eval:f1 micro": 0.98, "eval:precision micro": 0.98, "eval:recall micro": 0.97, "eval:f1 macro": 0.97, "eval:precision macro": 0.97, "eval:recall macro": 0.98, "eval:f1 weighted": 0.98, "eval:precision weighted": 0.99, "eval:recall weighted": 0.97}, "pre_update": {}, "post_update": {}}, {"round_no": 15, "pre_train": {"ts": 1682524276.877729, "eval:loss": 0.11327029019594193, "eval:acc": 0.9729729890823364, "eval:f1 micro": 0.97, "eval:precision micro": 0.97, "eval:recall micro": 0.97, "eval:f1 macro": 0.97, "eval:precision macro": 0.96, "eval:recall macro": 0.98, "eval:f1 weighted": 0.97, "eval:precision weighted": 0.98, "eval:recall weighted": 0.97}, "post_train": {"ts": 1682524303.3703814, "eval:loss": 0.114559605717659, "eval:acc": 0.9819819927215576, "eval:f1 micro": 0.99, "eval:precision micro": 0.99, "eval:recall micro": 0.98, "eval:f1 macro": 0.98, "eval:precision macro": 0.98, "eval:recall macro": 0.99, "eval:f1 weighted": 0.99, "eval:precision weighted": 0.99, "eval:recall weighted": 0.98}, "pre_update": {}, "post_update": {}}, {"round_no": 16, "pre_train": {"ts": 1682524316.129013, "eval:loss": 0.11022967845201492, "eval:acc": 0.9819819927215576, "eval:f1 micro": 0.98, "eval:precision micro": 0.98, "eval:recall micro": 0.98, "eval:f1 macro": 0.98, "eval:precision macro": 0.97, "eval:recall macro": 0.99, "eval:f1 weighted": 0.98, "eval:precision weighted": 0.98, "eval:recall weighted": 0.98}, "post_train": {"ts": 1682524343.1097133, "eval:loss": 0.13812164962291718, "eval:acc": 0.9729729890823364, "eval:f1 micro": 0.97, "eval:precision micro": 0.97, "eval:recall micro": 0.97, "eval:f1 macro": 0.97, "eval:precision macro": 0.96, "eval:recall macro": 0.98, "eval:f1 weighted": 0.97, "eval:precision weighted": 0.98, "eval:recall weighted": 0.97}, "pre_update": {}, "post_update": {}}, {"round_no": 17, "pre_train": {"ts": 1682524353.0528104, "eval:loss": 0.10622124373912811, "eval:acc": 0.9819819927215576, "eval:f1 micro": 0.98, "eval:precision micro": 0.98, "eval:recall micro": 0.98, "eval:f1 macro": 0.98, "eval:precision macro": 0.97, "eval:recall macro": 0.99, "eval:f1 weighted": 0.98, "eval:precision weighted": 0.98, "eval:recall weighted": 0.98}, "post_train": {"ts": 1682524381.4226892, "eval:loss": 0.12371841818094254, "eval:acc": 0.9819819927215576, "eval:f1 micro": 0.98, "eval:precision micro": 0.98, "eval:recall micro": 0.98, "eval:f1 macro": 0.98, "eval:precision macro": 0.97, "eval:recall macro": 0.99, "eval:f1 weighted": 0.98, "eval:precision weighted": 0.98, "eval:recall weighted": 0.98}, "pre_update": {}, "post_update": {}}, {"round_no": 18, "pre_train": {"ts": 1682524388.2560894, "eval:loss": 0.10572250187397003, "eval:acc": 0.9819819927215576, "eval:f1 micro": 0.98, "eval:precision micro": 0.98, "eval:recall micro": 0.98, "eval:f1 macro": 0.98, "eval:precision macro": 0.97, "eval:recall macro": 0.99, "eval:f1 weighted": 0.98, "eval:precision weighted": 0.98, "eval:recall weighted": 0.98}, "post_train": {"ts": 1682524415.1622913, "eval:loss": 0.12185518443584442, "eval:acc": 0.9729729890823364, "eval:f1 micro": 0.97, "eval:precision micro": 0.97, "eval:recall micro": 0.97, "eval:f1 macro": 0.97, "eval:precision macro": 0.96, "eval:recall macro": 0.98, "eval:f1 weighted": 0.97, "eval:precision weighted": 0.98, "eval:recall weighted": 0.97}, "pre_update": {}, "post_update": {}}, {"round_no": 19, "pre_train": {"ts": 1682524427.5876603, "eval:loss": 0.10273808985948563, "eval:acc": 0.9819819927215576, "eval:f1 micro": 0.99, "eval:precision micro": 0.99, "eval:recall micro": 0.98, "eval:f1 macro": 0.98, "eval:precision macro": 0.98, "eval:recall macro": 0.99, "eval:f1 weighted": 0.99, "eval:precision weighted": 0.99, "eval:recall weighted": 0.98}, "post_train": {"ts": 1682524457.004305, "eval:loss": 0.10513642430305481, "eval:acc": 0.9819819927215576, "eval:f1 micro": 0.98, "eval:precision micro": 0.98, "eval:recall micro": 0.98, "eval:f1 macro": 0.98, "eval:precision macro": 0.97, "eval:recall macro": 0.99, "eval:f1 weighted": 0.98, "eval:precision weighted": 0.98, "eval:recall weighted": 0.98}, "pre_update": {}, "post_update": {}}]
